Workbook

Sheet Participantes
A1: Seguimiento del Lote 1 — participantes y formularios
A2: Edita solo las celdas amarillas (columnas E a J y N). Las columnas B, C, D, K, L y M son fórmulas. Las situaciones que alguien deja en blanco se registran en la hoja Blancos. Código sin relación con el nombre de la persona.
A3: Código | B3: Formulario | C3: Páginas a imprimir | D3: Tipo | E3: Rango de edad | F3: Ocupación | G3: ¿Vive en Juliaca? | H3: ¿Trámite en el último año? | I3: Estado | J3: Fecha de aplicación | K3: Situaciones respondidas | L3: Situaciones del formulario | M3: % respondido | N3: Observaciones
A4: P01 | B4: =CHOOSE(MOD(VALUE(MID(A4,2,2))-1,5)+1,"A","B","C","D","E") -> A | C4: =INDEX(Formularios!$E$2:$E$6,MATCH(B4,Formularios!$A$2:$A$6,0)) -> 2–3 | D4: =IF(VALUE(MID(A4,2,2))<=Resumen!$B$4,"Base","Reserva") -> Base | I4: Pendiente | K4: =IF(OR(I4="Respondido",I4="Transcrito"),L4-COUNTIFS(Blancos!$A$4:$A$83,A4,Blancos!$F$4:$F$83,"OK"),"") | L4: =INDEX(Formularios!$B$2:$B$6,MATCH(B4,Formularios!$A$2:$A$6,0)) -> 12 | M4: =IF(K4="","",K4/L4)
A5: P02 | B5: =CHOOSE(MOD(VALUE(MID(A5,2,2))-1,5)+1,"A","B","C","D","E") -> B | C5: =INDEX(Formularios!$E$2:$E$6,MATCH(B5,Formularios!$A$2:$A$6,0)) -> 4–5 | D5: =IF(VALUE(MID(A5,2,2))<=Resumen!$B$4,"Base","Reserva") -> Base | I5: Pendiente | K5: =IF(OR(I5="Respondido",I5="Transcrito"),L5-COUNTIFS(Blancos!$A$4:$A$83,A5,Blancos!$F$4:$F$83,"OK"),"") | L5: =INDEX(Formularios!$B$2:$B$6,MATCH(B5,Formularios!$A$2:$A$6,0)) -> 11 | M5: =IF(K5="","",K5/L5)
A6: P03 | B6: =CHOOSE(MOD(VALUE(MID(A6,2,2))-1,5)+1,"A","B","C","D","E") -> C | C6: =INDEX(Formularios!$E$2:$E$6,MATCH(B6,Formularios!$A$2:$A$6,0)) -> 6–7 | D6: =IF(VALUE(MID(A6,2,2))<=Resumen!$B$4,"Base","Reserva") -> Base | I6: Pendiente | K6: =IF(OR(I6="Respondido",I6="Transcrito"),L6-COUNTIFS(Blancos!$A$4:$A$83,A6,Blancos!$F$4:$F$83,"OK"),"") | L6: =INDEX(Formularios!$B$2:$B$6,MATCH(B6,Formularios!$A$2:$A$6,0)) -> 11 | M6: =IF(K6="","",K6/L6)
A7: P04 | B7: =CHOOSE(MOD(VALUE(MID(A7,2,2))-1,5)+1,"A","B","C","D","E") -> D | C7: =INDEX(Formularios!$E$2:$E$6,MATCH(B7,Formularios!$A$2:$A$6,0)) -> 8–9 | D7: =IF(VALUE(MID(A7,2,2))<=Resumen!$B$4,"Base","Reserva") -> Base | I7: Pendiente | K7: =IF(OR(I7="Respondido",I7="Transcrito"),L7-COUNTIFS(Blancos!$A$4:$A$83,A7,Blancos!$F$4:$F$83,"OK"),"") | L7: =INDEX(Formularios!$B$2:$B$6,MATCH(B7,Formularios!$A$2:$A$6,0)) -> 11 | M7: =IF(K7="","",K7/L7)
A8: P05 | B8: =CHOOSE(MOD(VALUE(MID(A8,2,2))-1,5)+1,"A","B","C","D","E") -> E | C8: =INDEX(Formularios!$E$2:$E$6,MATCH(B8,Formularios!$A$2:$A$6,0)) -> 10–11 | D8: =IF(VALUE(MID(A8,2,2))<=Resumen!$B$4,"Base","Reserva") -> Base | I8: Pendiente | K8: =IF(OR(I8="Respondido",I8="Transcrito"),L8-COUNTIFS(Blancos!$A$4:$A$83,A8,Blancos!$F$4:$F$83,"OK"),"") | L8: =INDEX(Formularios!$B$2:$B$6,MATCH(B8,Formularios!$A$2:$A$6,0)) -> 11 | M8: =IF(K8="","",K8/L8)
A9: P06 | B9: =CHOOSE(MOD(VALUE(MID(A9,2,2))-1,5)+1,"A","B","C","D","E") -> A | C9: =INDEX(Formularios!$E$2:$E$6,MATCH(B9,Formularios!$A$2:$A$6,0)) -> 2–3 | D9: =IF(VALUE(MID(A9,2,2))<=Resumen!$B$4,"Base","Reserva") -> Base | I9: Pendiente | K9: =IF(OR(I9="Respondido",I9="Transcrito"),L9-COUNTIFS(Blancos!$A$4:$A$83,A9,Blancos!$F$4:$F$83,"OK"),"") | L9: =INDEX(Formularios!$B$2:$B$6,MATCH(B9,Formularios!$A$2:$A$6,0)) -> 12 | M9: =IF(K9="","",K9/L9)
A10: P07 | B10: =CHOOSE(MOD(VALUE(MID(A10,2,2))-1,5)+1,"A","B","C","D","E") -> B | C10: =INDEX(Formularios!$E$2:$E$6,MATCH(B10,Formularios!$A$2:$A$6,0)) -> 4–5 | D10: =IF(VALUE(MID(A10,2,2))<=Resumen!$B$4,"Base","Reserva") -> Base | I10: Pendiente | K10: =IF(OR(I10="Respondido",I10="Transcrito"),L10-COUNTIFS(Blancos!$A$4:$A$83,A10,Blancos!$F$4:$F$83,"OK"),"") | L10: =INDEX(Formularios!$B$2:$B$6,MATCH(B10,Formularios!$A$2:$A$6,0)) -> 11 | M10: =IF(K10="","",K10/L10)
A11: P08 | B11: =CHOOSE(MOD(VALUE(MID(A11,2,2))-1,5)+1,"A","B","C","D","E") -> C | C11: =INDEX(Formularios!$E$2:$E$6,MATCH(B11,Formularios!$A$2:$A$6,0)) -> 6–7 | D11: =IF(VALUE(MID(A11,2,2))<=Resumen!$B$4,"Base","Reserva") -> Base | I11: Pendiente | K11: =IF(OR(I11="Respondido",I11="Transcrito"),L11-COUNTIFS(Blancos!$A$4:$A$83,A11,Blancos!$F$4:$F$83,"OK"),"") | L11: =INDEX(Formularios!$B$2:$B$6,MATCH(B11,Formularios!$A$2:$A$6,0)) -> 11 | M11: =IF(K11="","",K11/L11)
A12: P09 | B12: =CHOOSE(MOD(VALUE(MID(A12,2,2))-1,5)+1,"A","B","C","D","E") -> D | C12: =INDEX(Formularios!$E$2:$E$6,MATCH(B12,Formularios!$A$2:$A$6,0)) -> 8–9 | D12: =IF(VALUE(MID(A12,2,2))<=Resumen!$B$4,"Base","Reserva") -> Base | I12: Pendiente | K12: =IF(OR(I12="Respondido",I12="Transcrito"),L12-COUNTIFS(Blancos!$A$4:$A$83,A12,Blancos!$F$4:$F$83,"OK"),"") | L12: =INDEX(Formularios!$B$2:$B$6,MATCH(B12,Formularios!$A$2:$A$6,0)) -> 11 | M12: =IF(K12="","",K12/L12)
A13: P10 | B13: =CHOOSE(MOD(VALUE(MID(A13,2,2))-1,5)+1,"A","B","C","D","E") -> E | C13: =INDEX(Formularios!$E$2:$E$6,MATCH(B13,Formularios!$A$2:$A$6,0)) -> 10–11 | D13: =IF(VALUE(MID(A13,2,2))<=Resumen!$B$4,"Base","Reserva") -> Base | I13: Pendiente | K13: =IF(OR(I13="Respondido",I13="Transcrito"),L13-COUNTIFS(Blancos!$A$4:$A$83,A13,Blancos!$F$4:$F$83,"OK"),"") | L13: =INDEX(Formularios!$B$2:$B$6,MATCH(B13,Formularios!$A$2:$A$6,0)) -> 11 | M13: =IF(K13="","",K13/L13)
A14: P11 | B14: =CHOOSE(MOD(VALUE(MID(A14,2,2))-1,5)+1,"A","B","C","D","E") -> A | C14: =INDEX(Formularios!$E$2:$E$6,MATCH(B14,Formularios!$A$2:$A$6,0)) -> 2–3 | D14: =IF(VALUE(MID(A14,2,2))<=Resumen!$B$4,"Base","Reserva") -> Base | I14: Pendiente | K14: =IF(OR(I14="Respondido",I14="Transcrito"),L14-COUNTIFS(Blancos!$A$4:$A$83,A14,Blancos!$F$4:$F$83,"OK"),"") | L14: =INDEX(Formularios!$B$2:$B$6,MATCH(B14,Formularios!$A$2:$A$6,0)) -> 12 | M14: =IF(K14="","",K14/L14)
A15: P12 | B15: =CHOOSE(MOD(VALUE(MID(A15,2,2))-1,5)+1,"A","B","C","D","E") -> B | C15: =INDEX(Formularios!$E$2:$E$6,MATCH(B15,Formularios!$A$2:$A$6,0)) -> 4–5 | D15: =IF(VALUE(MID(A15,2,2))<=Resumen!$B$4,"Base","Reserva") -> Base | I15: Pendiente | K15: =IF(OR(I15="Respondido",I15="Transcrito"),L15-COUNTIFS(Blancos!$A$4:$A$83,A15,Blancos!$F$4:$F$83,"OK"),"") | L15: =INDEX(Formularios!$B$2:$B$6,MATCH(B15,Formularios!$A$2:$A$6,0)) -> 11 | M15: =IF(K15="","",K15/L15)
... A28: P25 | B28: =CHOOSE(MOD(VALUE(MID(A28,2,2))-1,5)+1,"A","B","C","D","E") -> E | C28: =INDEX(Formularios!$E$2:$E$6,MATCH(B28,Formularios!$A$2:$A$6,0)) -> 10–11 | D28: =IF(VALUE(MID(A28,2,2))<=Resumen!$B$4,"Base","Reserva") -> Reserva | I28: Pendiente | K28: =IF(OR(I28="Respondido",I28="Transcrito"),L28-COUNTIFS(Blancos!$A$4:$A$83,A28,Blancos!$F$4:$F$83,"OK"),"") | L28: =INDEX(Formularios!$B$2:$B$6,MATCH(B28,Formularios!$A$2:$A$6,0)) -> 11 | M28: =IF(K28="","",K28/L28)
A30: Ejemplo de fila completada (solo muestra el formato; no cuenta en los conteos):
A31: P01 | B31: A | C31: 2–3 | D31: Base | E31: 30–44 | F31: Comerciante | G31: Sí | H31: Sí | I31: Transcrito | J31: 46300 | K31: 11 | L31: 12 | M31: 0.91666667 | N31: Dejó sin responder la situación S16 (se registra en Blancos)

Sheet Blancos
A1: Situaciones dejadas en blanco
A2: Una fila por cada situación que una persona dejó sin responder (código en A, situación en B; ej.: P16 y S16). Solo cuentan las filas con Verificación = OK de personas con estado Transcrito (una situación repetida o de otro formulario se marca para corregir). Celdas amarillas = editar; C a F son fórmulas.
A3: Código | B3: Situación | C3: Formulario del participante | D3: Formulario de la situación | E3: Estado del participante | F3: Verificación | G3: Nota
C4: =IF(A4="","",IFERROR(INDEX(Participantes!$B$4:$B$28,MATCH(A4,Participantes!$A$4:$A$28,0)),"Código no válido")) | D4: =IF(B4="","",IFERROR(INDEX(Situaciones!$B$4:$B$59,MATCH(B4,Situaciones!$A$4:$A$59,0)),"Situación no válida")) | E4: =IF(A4="","",IFERROR(INDEX(Participantes!$I$4:$I$28,MATCH(A4,Participantes!$A$4:$A$28,0)),"")) | F4: =IF(OR(A4="",B4=""),"",IF(C4<>D4,"Revisar: la situación no es de su formulario",IF(COUNTIFS($A$4:$A4,A4,$B$4:$B4,B4)>1,"Revisar: repetida","OK")))
C5: =IF(A5="","",IFERROR(INDEX(Participantes!$B$4:$B$28,MATCH(A5,Participantes!$A$4:$A$28,0)),"Código no válido")) | D5: =IF(B5="","",IFERROR(INDEX(Situaciones!$B$4:$B$59,MATCH(B5,Situaciones!$A$4:$A$59,0)),"Situación no válida")) | E5: =IF(A5="","",IFERROR(INDEX(Participantes!$I$4:$I$28,MATCH(A5,Participantes!$A$4:$A$28,0)),"")) | F5: =IF(OR(A5="",B5=""),"",IF(C5<>D5,"Revisar: la situación no es de su formulario",IF(COUNTIFS($A$4:$A5,A5,$B$4:$B5,B5)>1,"Revisar: repetida","OK")))
C6: =IF(A6="","",IFERROR(INDEX(Participantes!$B$4:$B$28,MATCH(A6,Participantes!$A$4:$A$28,0)),"Código no válido")) | D6: =IF(B6="","",IFERROR(INDEX(Situaciones!$B$4:$B$59,MATCH(B6,Situaciones!$A$4:$A$59,0)),"Situación no válida")) | E6: =IF(A6="","",IFERROR(INDEX(Participantes!$I$4:$I$28,MATCH(A6,Participantes!$A$4:$A$28,0)),"")) | F6: =IF(OR(A6="",B6=""),"",IF(C6<>D6,"Revisar: la situación no es de su formulario",IF(COUNTIFS($A$4:$A6,A6,$B$4:$B6,B6)>1,"Revisar: repetida","OK")))
C7: =IF(A7="","",IFERROR(INDEX(Participantes!$B$4:$B$28,MATCH(A7,Participantes!$A$4:$A$28,0)),"Código no válido")) | D7: =IF(B7="","",IFERROR(INDEX(Situaciones!$B$4:$B$59,MATCH(B7,Situaciones!$A$4:$A$59,0)),"Situación no válida")) | E7: =IF(A7="","",IFERROR(INDEX(Participantes!$I$4:$I$28,MATCH(A7,Participantes!$A$4:$A$28,0)),"")) | F7: =IF(OR(A7="",B7=""),"",IF(C7<>D7,"Revisar: la situación no es de su formulario",IF(COUNTIFS($A$4:$A7,A7,$B$4:$B7,B7)>1,"Revisar: repetida","OK")))
C8: =IF(A8="","",IFERROR(INDEX(Participantes!$B$4:$B$28,MATCH(A8,Participantes!$A$4:$A$28,0)),"Código no válido")) | D8: =IF(B8="","",IFERROR(INDEX(Situaciones!$B$4:$B$59,MATCH(B8,Situaciones!$A$4:$A$59,0)),"Situación no válida")) | E8: =IF(A8="","",IFERROR(INDEX(Participantes!$I$4:$I$28,MATCH(A8,Participantes!$A$4:$A$28,0)),"")) | F8: =IF(OR(A8="",B8=""),"",IF(C8<>D8,"Revisar: la situación no es de su formulario",IF(COUNTIFS($A$4:$A8,A8,$B$4:$B8,B8)>1,"Revisar: repetida","OK")))
C9: =IF(A9="","",IFERROR(INDEX(Participantes!$B$4:$B$28,MATCH(A9,Participantes!$A$4:$A$28,0)),"Código no válido")) | D9: =IF(B9="","",IFERROR(INDEX(Situaciones!$B$4:$B$59,MATCH(B9,Situaciones!$A$4:$A$59,0)),"Situación no válida")) | E9: =IF(A9="","",IFERROR(INDEX(Participantes!$I$4:$I$28,MATCH(A9,Participantes!$A$4:$A$28,0)),"")) | F9: =IF(OR(A9="",B9=""),"",IF(C9<>D9,"Revisar: la situación no es de su formulario",IF(COUNTIFS($A$4:$A9,A9,$B$4:$B9,B9)>1,"Revisar: repetida","OK")))
C10: =IF(A10="","",IFERROR(INDEX(Participantes!$B$4:$B$28,MATCH(A10,Participantes!$A$4:$A$28,0)),"Código no válido")) | D10: =IF(B10="","",IFERROR(INDEX(Situaciones!$B$4:$B$59,MATCH(B10,Situaciones!$A$4:$A$59,0)),"Situación no válida")) | E10: =IF(A10="","",IFERROR(INDEX(Participantes!$I$4:$I$28,MATCH(A10,Participantes!$A$4:$A$28,0)),"")) | F10: =IF(OR(A10="",B10=""),"",IF(C10<>D10,"Revisar: la situación no es de su formulario",IF(COUNTIFS($A$4:$A10,A10,$B$4:$B10,B10)>1,"Revisar: repetida","OK")))
C11: =IF(A11="","",IFERROR(INDEX(Participantes!$B$4:$B$28,MATCH(A11,Participantes!$A$4:$A$28,0)),"Código no válido")) | D11: =IF(B11="","",IFERROR(INDEX(Situaciones!$B$4:$B$59,MATCH(B11,Situaciones!$A$4:$A$59,0)),"Situación no válida")) | E11: =IF(A11="","",IFERROR(INDEX(Participantes!$I$4:$I$28,MATCH(A11,Participantes!$A$4:$A$28,0)),"")) | F11: =IF(OR(A11="",B11=""),"",IF(C11<>D11,"Revisar: la situación no es de su formulario",IF(COUNTIFS($A$4:$A11,A11,$B$4:$B11,B11)>1,"Revisar: repetida","OK")))
C12: =IF(A12="","",IFERROR(INDEX(Participantes!$B$4:$B$28,MATCH(A12,Participantes!$A$4:$A$28,0)),"Código no válido")) | D12: =IF(B12="","",IFERROR(INDEX(Situaciones!$B$4:$B$59,MATCH(B12,Situaciones!$A$4:$A$59,0)),"Situación no válida")) | E12: =IF(A12="","",IFERROR(INDEX(Participantes!$I$4:$I$28,MATCH(A12,Participantes!$A$4:$A$28,0)),"")) | F12: =IF(OR(A12="",B12=""),"",IF(C12<>D12,"Revisar: la situación no es de su formulario",IF(COUNTIFS($A$4:$A12,A12,$B$4:$B12,B12)>1,"Revisar: repetida","OK")))
C13: =IF(A13="","",IFERROR(INDEX(Participantes!$B$4:$B$28,MATCH(A13,Participantes!$A$4:$A$28,0)),"Código no válido")) | D13: =IF(B13="","",IFERROR(INDEX(Situaciones!$B$4:$B$59,MATCH(B13,Situaciones!$A$4:$A$59,0)),"Situación no válida")) | E13: =IF(A13="","",IFERROR(INDEX(Participantes!$I$4:$I$28,MATCH(A13,Participantes!$A$4:$A$28,0)),"")) | F13: =IF(OR(A13="",B13=""),"",IF(C13<>D13,"Revisar: la situación no es de su formulario",IF(COUNTIFS($A$4:$A13,A13,$B$4:$B13,B13)>1,"Revisar: repetida","OK")))
C14: =IF(A14="","",IFERROR(INDEX(Participantes!$B$4:$B$28,MATCH(A14,Participantes!$A$4:$A$28,0)),"Código no válido")) | D14: =IF(B14="","",IFERROR(INDEX(Situaciones!$B$4:$B$59,MATCH(B14,Situaciones!$A$4:$A$59,0)),"Situación no válida")) | E14: =IF(A14="","",IFERROR(INDEX(Participantes!$I$4:$I$28,MATCH(A14,Participantes!$A$4:$A$28,0)),"")) | F14: =IF(OR(A14="",B14=""),"",IF(C14<>D14,"Revisar: la situación no es de su formulario",IF(COUNTIFS($A$4:$A14,A14,$B$4:$B14,B14)>1,"Revisar: repetida","OK")))
C15: =IF(A15="","",IFERROR(INDEX(Participantes!$B$4:$B$28,MATCH(A15,Participantes!$A$4:$A$28,0)),"Código no válido")) | D15: =IF(B15="","",IFERROR(INDEX(Situaciones!$B$4:$B$59,MATCH(B15,Situaciones!$A$4:$A$59,0)),"Situación no válida")) | E15: =IF(A15="","",IFERROR(INDEX(Participantes!$I$4:$I$28,MATCH(A15,Participantes!$A$4:$A$28,0)),"")) | F15: =IF(OR(A15="",B15=""),"",IF(C15<>D15,"Revisar: la situación no es de su formulario",IF(COUNTIFS($A$4:$A15,A15,$B$4:$B15,B15)>1,"Revisar: repetida","OK")))
... C83: =IF(A83="","",IFERROR(INDEX(Participantes!$B$4:$B$28,MATCH(A83,Participantes!$A$4:$A$28,0)),"Código no válido")) | D83: =IF(B83="","",IFERROR(INDEX(Situaciones!$B$4:$B$59,MATCH(B83,Situaciones!$A$4:$A$59,0)),"Situación no válida")) | E83: =IF(A83="","",IFERROR(INDEX(Participantes!$I$4:$I$28,MATCH(A83,Participantes!$A$4:$A$28,0)),"")) | F83: =IF(OR(A83="",B83=""),"",IF(C83<>D83,"Revisar: la situación no es de su formulario",IF(COUNTIFS($A$4:$A83,A83,$B$4:$B83,B83)>1,"Revisar: repetida","OK")))

Sheet Resumen
A1: Resumen de cobertura del Lote 1
A2: Celdas amarillas = parámetros editables. El resto son fórmulas que leen las hojas Participantes, Blancos y Cobertura.
A3: Parámetro | B3: Valor | C3: Fuente / criterio
A4: Participantes base (rotación A–E) | B4: 20 | C4: Guía de aplicación del Lote 1 (Lote1_Formularios_lenguaje_real_v2): 20 personas, mínimo 15, ideal 25 a 30. P21–P25 quedan como reserva.
A5: Meta de frases reales por intención | B5: 4 | C5: 20 personas ÷ 5 formularios = 4 respuestas por situación (4 frases reales por intención). Guía de aplicación.
A6: Mínimo de frases reales por intención | B6: 3 | C6: La Parte B se detiene si alguna intención queda con menos de 3 frases reales (Instrucciones_ClaudeCode_lote_real_v2.md, paso B1). Se usa también como mínimo de personas por formulario.
A7: Mínimo de participantes transcritos para iniciar la Parte B | B7: 15 | C7: Mínimo indicado en la guía de aplicación del Lote 1.
A8: Rangos de edad distintos para variedad “Buena” | B8: 3 | C8: Criterio de esta hoja para reducir el sesgo de una muestra de conveniencia; no es una norma.
A10: Cobertura por formulario (personas)
A11: Formulario | B11: Situaciones | C11: Asignados (incl. reserva) | D11: Transcritos | E11: Meta de personas | F11: Faltan para la meta | G11: Personas (estado)
A12: A | B12: =INDEX(Formularios!$B$2:$B$6,MATCH(A12,Formularios!$A$2:$A$6,0)) -> 12 | C12: =COUNTIF(Participantes!$B$4:$B$28,A12) -> 5 | D12: =COUNTIFS(Participantes!$B$4:$B$28,A12,Participantes!$I$4:$I$28,"Transcrito") -> 0 | E12: =$B$5 -> 4 | F12: =MAX(0,E12-D12) -> 4 | G12: =IF(D12>=$B$5,"Meta cumplida",IF(D12>=$B$6,"Mínimo alcanzado","Insuficiente")) -> Insuficiente
A13: B | B13: =INDEX(Formularios!$B$2:$B$6,MATCH(A13,Formularios!$A$2:$A$6,0)) -> 11 | C13: =COUNTIF(Participantes!$B$4:$B$28,A13) -> 5 | D13: =COUNTIFS(Participantes!$B$4:$B$28,A13,Participantes!$I$4:$I$28,"Transcrito") -> 0 | E13: =$B$5 -> 4 | F13: =MAX(0,E13-D13) -> 4 | G13: =IF(D13>=$B$5,"Meta cumplida",IF(D13>=$B$6,"Mínimo alcanzado","Insuficiente")) -> Insuficiente
A14: C | B14: =INDEX(Formularios!$B$2:$B$6,MATCH(A14,Formularios!$A$2:$A$6,0)) -> 11 | C14: =COUNTIF(Participantes!$B$4:$B$28,A14) -> 5 | D14: =COUNTIFS(Participantes!$B$4:$B$28,A14,Participantes!$I$4:$I$28,"Transcrito") -> 0 | E14: =$B$5 -> 4 | F14: =MAX(0,E14-D14) -> 4 | G14: =IF(D14>=$B$5,"Meta cumplida",IF(D14>=$B$6,"Mínimo alcanzado","Insuficiente")) -> Insuficiente
A15: D | B15: =INDEX(Formularios!$B$2:$B$6,MATCH(A15,Formularios!$A$2:$A$6,0)) -> 11 | C15: =COUNTIF(Participantes!$B$4:$B$28,A15) -> 5 | D15: =COUNTIFS(Participantes!$B$4:$B$28,A15,Participantes!$I$4:$I$28,"Transcrito") -> 0 | E15: =$B$5 -> 4 | F15: =MAX(0,E15-D15) -> 4 | G15: =IF(D15>=$B$5,"Meta cumplida",IF(D15>=$B$6,"Mínimo alcanzado","Insuficiente")) -> Insuficiente
A16: E | B16: =INDEX(Formularios!$B$2:$B$6,MATCH(A16,Formularios!$A$2:$A$6,0)) -> 11 | C16: =COUNTIF(Participantes!$B$4:$B$28,A16) -> 5 | D16: =COUNTIFS(Participantes!$B$4:$B$28,A16,Participantes!$I$4:$I$28,"Transcrito") -> 0 | E16: =$B$5 -> 4 | F16: =MAX(0,E16-D16) -> 4 | G16: =IF(D16>=$B$5,"Meta cumplida",IF(D16>=$B$6,"Mínimo alcanzado","Insuficiente")) -> Insuficiente
A17: Total | B17: =SUM(B12:B16) -> 56 | C17: =SUM(C12:C16) -> 25 | D17: =SUM(D12:D16) -> 0 | E17: =SUM(E12:E16) -> 20 | F17: =SUM(F12:F16) -> 20 | G17: =IF(AND(D17>=$B$7,MIN(D12:D16)>=$B$6),"Personas suficientes","Faltan personas") -> Faltan personas
A19: Cobertura por intención (frases reales)
A20: Indicador | B20: Valor | C20: Detalle
A21: Intenciones con la meta cumplida | B21: =COUNTIF(Cobertura!$G$4:$G$57,"Meta cumplida") -> 0 | C21: ="de "&COUNTA(Cobertura!$A$4:$A$57)&" intenciones" -> de 54 intenciones
A22: Intenciones en el mínimo (por debajo de la meta) | B22: =COUNTIF(Cobertura!$G$4:$G$57,"Mínimo alcanzado") -> 0 | C22: Revisar la hoja Cobertura (columna Estado) y, si hay reserva, activarla.
A23: Intenciones por debajo del mínimo | B23: =COUNTIF(Cobertura!$G$4:$G$57,"Insuficiente") -> 54 | C23: La Parte B se detiene si este valor es mayor que 0.
A24: Frases reales en la intención con menos respuestas | B24: =MIN(Cobertura!$D$4:$D$57) -> 0 | C24: Respuestas = transcritos del formulario − blancos registrados (suma de todas las situaciones de la intención).
A25: Estado general | B25: =IF(AND(D17>=$B$7,B24>=$B$6),"Listo para la Parte B","Aún no") -> Aún no | C25: Requiere: participantes transcritos ≥ mínimo y cada intención con al menos el mínimo de frases reales.
A27: Mezcla de edades por formulario
A28: Formulario | B28: =Listas!$A$2 -> 18–29 | C28: =Listas!$A$3 -> 30–44 | D28: =Listas!$A$4 -> 45–59 | E28: =Listas!$A$5 -> 60 a más | F28: Rangos distintos | G28: Variedad
A29: A | B29: =COUNTIFS(Participantes!$B$4:$B$28,$A29,Participantes!$E$4:$E$28,B$28) -> 0 | C29: =COUNTIFS(Participantes!$B$4:$B$28,$A29,Participantes!$E$4:$E$28,C$28) -> 0 | D29: =COUNTIFS(Participantes!$B$4:$B$28,$A29,Participantes!$E$4:$E$28,D$28) -> 0 | E29: =COUNTIFS(Participantes!$B$4:$B$28,$A29,Participantes!$E$4:$E$28,E$28) -> 0 | F29: =SUMPRODUCT(--(B29:E29>0)) -> 0 | G29: =IF(SUM(B29:E29)=0,"",IF(F29>=$B$8,"Buena",IF(F29>=$B$8-1,"Media","Baja")))
A30: B | B30: =COUNTIFS(Participantes!$B$4:$B$28,$A30,Participantes!$E$4:$E$28,B$28) -> 0 | C30: =COUNTIFS(Participantes!$B$4:$B$28,$A30,Participantes!$E$4:$E$28,C$28) -> 0 | D30: =COUNTIFS(Participantes!$B$4:$B$28,$A30,Participantes!$E$4:$E$28,D$28) -> 0 | E30: =COUNTIFS(Participantes!$B$4:$B$28,$A30,Participantes!$E$4:$E$28,E$28) -> 0 | F30: =SUMPRODUCT(--(B30:E30>0)) -> 0 | G30: =IF(SUM(B30:E30)=0,"",IF(F30>=$B$8,"Buena",IF(F30>=$B$8-1,"Media","Baja")))
A31: C | B31: =COUNTIFS(Participantes!$B$4:$B$28,$A31,Participantes!$E$4:$E$28,B$28) -> 0 | C31: =COUNTIFS(Participantes!$B$4:$B$28,$A31,Participantes!$E$4:$E$28,C$28) -> 0 | D31: =COUNTIFS(Participantes!$B$4:$B$28,$A31,Participantes!$E$4:$E$28,D$28) -> 0 | E31: =COUNTIFS(Participantes!$B$4:$B$28,$A31,Participantes!$E$4:$E$28,E$28) -> 0 | F31: =SUMPRODUCT(--(B31:E31>0)) -> 0 | G31: =IF(SUM(B31:E31)=0,"",IF(F31>=$B$8,"Buena",IF(F31>=$B$8-1,"Media","Baja")))
A32: D | B32: =COUNTIFS(Participantes!$B$4:$B$28,$A32,Participantes!$E$4:$E$28,B$28) -> 0 | C32: =COUNTIFS(Participantes!$B$4:$B$28,$A32,Participantes!$E$4:$E$28,C$28) -> 0 | D32: =COUNTIFS(Participantes!$B$4:$B$28,$A32,Participantes!$E$4:$E$28,D$28) -> 0 | E32: =COUNTIFS(Participantes!$B$4:$B$28,$A32,Participantes!$E$4:$E$28,E$28) -> 0 | F32: =SUMPRODUCT(--(B32:E32>0)) -> 0 | G32: =IF(SUM(B32:E32)=0,"",IF(F32>=$B$8,"Buena",IF(F32>=$B$8-1,"Media","Baja")))
A33: E | B33: =COUNTIFS(Participantes!$B$4:$B$28,$A33,Participantes!$E$4:$E$28,B$28) -> 0 | C33: =COUNTIFS(Participantes!$B$4:$B$28,$A33,Participantes!$E$4:$E$28,C$28) -> 0 | D33: =COUNTIFS(Participantes!$B$4:$B$28,$A33,Participantes!$E$4:$E$28,D$28) -> 0 | E33: =COUNTIFS(Participantes!$B$4:$B$28,$A33,Participantes!$E$4:$E$28,E$28) -> 0 | F33: =SUMPRODUCT(--(B33:E33>0)) -> 0 | G33: =IF(SUM(B33:E33)=0,"",IF(F33>=$B$8,"Buena",IF(F33>=$B$8-1,"Media","Baja")))
A34: Cuenta solo a los participantes con rango de edad registrado en la hoja Participantes.

Sheet Cobertura
A1: Cobertura por intención
A2: Frases reales por intención = suma, sobre sus situaciones, de (personas transcritas del formulario − blancos registrados). Todo son fórmulas; los parámetros están en Resumen.
A3: Intención | B3: Categoría | C3: Situaciones | D3: Respuestas | E3: Meta | F3: Faltan para la meta | G3: Estado
A4: licencia_funcionamiento_requisitos | B4: Licencias y autorizaciones | C4: =COUNTIF(Situaciones!$C$4:$C$59,A4) -> 1 | D4: =SUMIF(Situaciones!$C$4:$C$59,A4,Situaciones!$F$4:$F$59) -> 0 | E4: =Resumen!$B$5 -> 4 | F4: =MAX(0,E4-D4) -> 4 | G4: =IF(D4>=E4,"Meta cumplida",IF(D4>=Resumen!$B$6,"Mínimo alcanzado","Insuficiente")) -> Insuficiente
A5: licencia_funcionamiento_costo | B5: Licencias y autorizaciones | C5: =COUNTIF(Situaciones!$C$4:$C$59,A5) -> 1 | D5: =SUMIF(Situaciones!$C$4:$C$59,A5,Situaciones!$F$4:$F$59) -> 0 | E5: =Resumen!$B$5 -> 4 | F5: =MAX(0,E5-D5) -> 4 | G5: =IF(D5>=E5,"Meta cumplida",IF(D5>=Resumen!$B$6,"Mínimo alcanzado","Insuficiente")) -> Insuficiente
A6: licencia_funcionamiento_plazo | B6: Licencias y autorizaciones | C6: =COUNTIF(Situaciones!$C$4:$C$59,A6) -> 1 | D6: =SUMIF(Situaciones!$C$4:$C$59,A6,Situaciones!$F$4:$F$59) -> 0 | E6: =Resumen!$B$5 -> 4 | F6: =MAX(0,E6-D6) -> 4 | G6: =IF(D6>=E6,"Meta cumplida",IF(D6>=Resumen!$B$6,"Mínimo alcanzado","Insuficiente")) -> Insuficiente
A7: licencia_edificacion_requisitos | B7: Licencias y autorizaciones | C7: =COUNTIF(Situaciones!$C$4:$C$59,A7) -> 1 | D7: =SUMIF(Situaciones!$C$4:$C$59,A7,Situaciones!$F$4:$F$59) -> 0 | E7: =Resumen!$B$5 -> 4 | F7: =MAX(0,E7-D7) -> 4 | G7: =IF(D7>=E7,"Meta cumplida",IF(D7>=Resumen!$B$6,"Mínimo alcanzado","Insuficiente")) -> Insuficiente
A8: licencia_edificacion_costo | B8: Licencias y autorizaciones | C8: =COUNTIF(Situaciones!$C$4:$C$59,A8) -> 1 | D8: =SUMIF(Situaciones!$C$4:$C$59,A8,Situaciones!$F$4:$F$59) -> 0 | E8: =Resumen!$B$5 -> 4 | F8: =MAX(0,E8-D8) -> 4 | G8: =IF(D8>=E8,"Meta cumplida",IF(D8>=Resumen!$B$6,"Mínimo alcanzado","Insuficiente")) -> Insuficiente
A9: renovacion_licencia | B9: Licencias y autorizaciones | C9: =COUNTIF(Situaciones!$C$4:$C$59,A9) -> 1 | D9: =SUMIF(Situaciones!$C$4:$C$59,A9,Situaciones!$F$4:$F$59) -> 0 | E9: =Resumen!$B$5 -> 4 | F9: =MAX(0,E9-D9) -> 4 | G9: =IF(D9>=E9,"Meta cumplida",IF(D9>=Resumen!$B$6,"Mínimo alcanzado","Insuficiente")) -> Insuficiente
A10: consulta_deuda_predial | B10: Tributos y pagos municipales | C10: =COUNTIF(Situaciones!$C$4:$C$59,A10) -> 1 | D10: =SUMIF(Situaciones!$C$4:$C$59,A10,Situaciones!$F$4:$F$59) -> 0 | E10: =Resumen!$B$5 -> 4 | F10: =MAX(0,E10-D10) -> 4 | G10: =IF(D10>=E10,"Meta cumplida",IF(D10>=Resumen!$B$6,"Mínimo alcanzado","Insuficiente")) -> Insuficiente
A11: pago_predial_como | B11: Tributos y pagos municipales | C11: =COUNTIF(Situaciones!$C$4:$C$59,A11) -> 1 | D11: =SUMIF(Situaciones!$C$4:$C$59,A11,Situaciones!$F$4:$F$59) -> 0 | E11: =Resumen!$B$5 -> 4 | F11: =MAX(0,E11-D11) -> 4 | G11: =IF(D11>=E11,"Meta cumplida",IF(D11>=Resumen!$B$6,"Mínimo alcanzado","Insuficiente")) -> Insuficiente
A12: pago_arbitrios | B12: Tributos y pagos municipales | C12: =COUNTIF(Situaciones!$C$4:$C$59,A12) -> 1 | D12: =SUMIF(Situaciones!$C$4:$C$59,A12,Situaciones!$F$4:$F$59) -> 0 | E12: =Resumen!$B$5 -> 4 | F12: =MAX(0,E12-D12) -> 4 | G12: =IF(D12>=E12,"Meta cumplida",IF(D12>=Resumen!$B$6,"Mínimo alcanzado","Insuficiente")) -> Insuficiente
A13: impuesto_alcabala | B13: Tributos y pagos municipales | C13: =COUNTIF(Situaciones!$C$4:$C$59,A13) -> 1 | D13: =SUMIF(Situaciones!$C$4:$C$59,A13,Situaciones!$F$4:$F$59) -> 0 | E13: =Resumen!$B$5 -> 4 | F13: =MAX(0,E13-D13) -> 4 | G13: =IF(D13>=E13,"Meta cumplida",IF(D13>=Resumen!$B$6,"Mínimo alcanzado","Insuficiente")) -> Insuficiente
A14: fraccionamiento_deuda | B14: Tributos y pagos municipales | C14: =COUNTIF(Situaciones!$C$4:$C$59,A14) -> 1 | D14: =SUMIF(Situaciones!$C$4:$C$59,A14,Situaciones!$F$4:$F$59) -> 0 | E14: =Resumen!$B$5 -> 4 | F14: =MAX(0,E14-D14) -> 4 | G14: =IF(D14>=E14,"Meta cumplida",IF(D14>=Resumen!$B$6,"Mínimo alcanzado","Insuficiente")) -> Insuficiente
A15: constancia_no_adeudo | B15: Tributos y pagos municipales | C15: =COUNTIF(Situaciones!$C$4:$C$59,A15) -> 1 | D15: =SUMIF(Situaciones!$C$4:$C$59,A15,Situaciones!$F$4:$F$59) -> 0 | E15: =Resumen!$B$5 -> 4 | F15: =MAX(0,E15-D15) -> 4 | G15: =IF(D15>=E15,"Meta cumplida",IF(D15>=Resumen!$B$6,"Mínimo alcanzado","Insuficiente")) -> Insuficiente
... A57: repetir_informacion | B57: Interacción conversacional | C57: =COUNTIF(Situaciones!$C$4:$C$59,A57) -> 1 | D57: =SUMIF(Situaciones!$C$4:$C$59,A57,Situaciones!$F$4:$F$59) -> 0 | E57: =Resumen!$B$5 -> 4 | F57: =MAX(0,E57-D57) -> 4 | G57: =IF(D57>=E57,"Meta cumplida",IF(D57>=Resumen!$B$6,"Mínimo alcanzado","Insuficiente")) -> Insuficiente
A59: Las intenciones y categorías provienen del catálogo situaciones_lote1_v1.csv (valores fijos, en azul). fuera_de_alcance tiene 3 situaciones, por eso puede sumar más de 4 frases.

Sheet Situaciones
A1: Respuestas por situación
A2: Catálogo de las 56 situaciones (fijo) y su cálculo. Respuestas = personas transcritas del formulario − blancos válidos (Verificación = OK) registrados en la hoja Blancos.
A3: Situación | B3: Formulario | C3: Intención esperada | D3: Transcritos del formulario | E3: Blancos de transcritos | F3: Respuestas | G3: Texto de la situación
A4: S01 | B4: A | C4: licencia_funcionamiento_requisitos | D4: =COUNTIFS(Participantes!$B$4:$B$28,B4,Participantes!$I$4:$I$28,"Transcrito") -> 0 | E4: =COUNTIFS(Blancos!$B$4:$B$83,A4,Blancos!$E$4:$E$83,"Transcrito",Blancos!$F$4:$F$83,"OK") -> 0 | F4: =D4-E4 -> 0 | G4: Vas a abrir una tiendita en tu barrio y no sabes qué papeles te van a pedir en la municipalidad para poder atender legalmente.
A5: S02 | B5: B | C5: licencia_funcionamiento_costo | D5: =COUNTIFS(Participantes!$B$4:$B$28,B5,Participantes!$I$4:$I$28,"Transcrito") -> 0 | E5: =COUNTIFS(Blancos!$B$4:$B$83,A5,Blancos!$E$4:$E$83,"Transcrito",Blancos!$F$4:$F$83,"OK") -> 0 | F5: =D5-E5 -> 0 | G5: Ya sabes que necesitas un permiso de la municipalidad para tu negocio y quieres saber cuánto tendrías que pagar por él.
A6: S03 | B6: C | C6: licencia_funcionamiento_plazo | D6: =COUNTIFS(Participantes!$B$4:$B$28,B6,Participantes!$I$4:$I$28,"Transcrito") -> 0 | E6: =COUNTIFS(Blancos!$B$4:$B$83,A6,Blancos!$E$4:$E$83,"Transcrito",Blancos!$F$4:$F$83,"OK") -> 0 | F6: =D6-E6 -> 0 | G6: Entregaste tus papeles para el permiso de tu negocio y quieres saber cuántos días demoran en dártelo.
A7: S04 | B7: D | C7: licencia_edificacion_requisitos | D7: =COUNTIFS(Participantes!$B$4:$B$28,B7,Participantes!$I$4:$I$28,"Transcrito") -> 0 | E7: =COUNTIFS(Blancos!$B$4:$B$83,A7,Blancos!$E$4:$E$83,"Transcrito",Blancos!$F$4:$F$83,"OK") -> 0 | F7: =D7-E7 -> 0 | G7: Quieres construir un segundo piso en tu casa y quieres saber qué documentos tendrías que presentar antes de empezar la obra.
A8: S05 | B8: E | C8: licencia_edificacion_costo | D8: =COUNTIFS(Participantes!$B$4:$B$28,B8,Participantes!$I$4:$I$28,"Transcrito") -> 0 | E8: =COUNTIFS(Blancos!$B$4:$B$83,A8,Blancos!$E$4:$E$83,"Transcrito",Blancos!$F$4:$F$83,"OK") -> 0 | F8: =D8-E8 -> 0 | G8: Vas a construir en tu terreno y quieres saber cuánto cobra la municipalidad por autorizar la obra.
A9: S06 | B9: A | C9: renovacion_licencia | D9: =COUNTIFS(Participantes!$B$4:$B$28,B9,Participantes!$I$4:$I$28,"Transcrito") -> 0 | E9: =COUNTIFS(Blancos!$B$4:$B$83,A9,Blancos!$E$4:$E$83,"Transcrito",Blancos!$F$4:$F$83,"OK") -> 0 | F9: =D9-E9 -> 0 | G9: El permiso de funcionamiento de tu negocio ya se venció y quieres saber qué tienes que hacer para dejarlo vigente otra vez.
A10: S07 | B10: B | C10: consulta_deuda_predial | D10: =COUNTIFS(Participantes!$B$4:$B$28,B10,Participantes!$I$4:$I$28,"Transcrito") -> 0 | E10: =COUNTIFS(Blancos!$B$4:$B$83,A10,Blancos!$E$4:$E$83,"Transcrito",Blancos!$F$4:$F$83,"OK") -> 0 | F10: =D10-E10 -> 0 | G10: Quieres saber si debes impuestos por tu casa o terreno, y cuánto sería.
A11: S08 | B11: C | C11: pago_predial_como | D11: =COUNTIFS(Participantes!$B$4:$B$28,B11,Participantes!$I$4:$I$28,"Transcrito") -> 0 | E11: =COUNTIFS(Blancos!$B$4:$B$83,A11,Blancos!$E$4:$E$83,"Transcrito",Blancos!$F$4:$F$83,"OK") -> 0 | F11: =D11-E11 -> 0 | G11: Ya sabes que debes pagar el impuesto de tu casa y quieres saber dónde o de qué forma puedes hacerlo.
A12: S09 | B12: D | C12: pago_arbitrios | D12: =COUNTIFS(Participantes!$B$4:$B$28,B12,Participantes!$I$4:$I$28,"Transcrito") -> 0 | E12: =COUNTIFS(Blancos!$B$4:$B$83,A12,Blancos!$E$4:$E$83,"Transcrito",Blancos!$F$4:$F$83,"OK") -> 0 | F12: =D12-E12 -> 0 | G12: Te llegó un cobro por el recojo de basura, la limpieza de calles y el serenazgo, y quieres saber cómo pagarlo.
A13: S10 | B13: E | C13: impuesto_alcabala | D13: =COUNTIFS(Participantes!$B$4:$B$28,B13,Participantes!$I$4:$I$28,"Transcrito") -> 0 | E13: =COUNTIFS(Blancos!$B$4:$B$83,A13,Blancos!$E$4:$E$83,"Transcrito",Blancos!$F$4:$F$83,"OK") -> 0 | F13: =D13-E13 -> 0 | G13: Acabas de comprar un terreno y te dijeron que hay un impuesto por esa compra; quieres saber de qué trata y cómo se paga.
A14: S11 | B14: A | C14: fraccionamiento_deuda | D14: =COUNTIFS(Participantes!$B$4:$B$28,B14,Participantes!$I$4:$I$28,"Transcrito") -> 0 | E14: =COUNTIFS(Blancos!$B$4:$B$83,A14,Blancos!$E$4:$E$83,"Transcrito",Blancos!$F$4:$F$83,"OK") -> 0 | F14: =D14-E14 -> 0 | G14: Debes varios años de impuestos municipales y no puedes pagar todo de golpe; quieres saber si puedes pagarlo poco a poco.
A15: S12 | B15: B | C15: constancia_no_adeudo | D15: =COUNTIFS(Participantes!$B$4:$B$28,B15,Participantes!$I$4:$I$28,"Transcrito") -> 0 | E15: =COUNTIFS(Blancos!$B$4:$B$83,A15,Blancos!$E$4:$E$83,"Transcrito",Blancos!$F$4:$F$83,"OK") -> 0 | F15: =D15-E15 -> 0 | G15: Te piden un papel que demuestre que no tienes deudas con la municipalidad y quieres saber cómo conseguirlo.
... A59: S56 | B59: A | C59: repetir_informacion | D59: =COUNTIFS(Participantes!$B$4:$B$28,B59,Participantes!$I$4:$I$28,"Transcrito") -> 0 | E59: =COUNTIFS(Blancos!$B$4:$B$83,A59,Blancos!$E$4:$E$83,"Transcrito",Blancos!$F$4:$F$83,"OK") -> 0 | F59: =D59-E59 -> 0 | G59: El asistente te dio una información pero no alcanzaste a leerla ni a anotarla. ¿Cómo le pedirías que te la repita?

Sheet Formularios
A1: Formulario | B1: Situaciones | C1: Pág. inicial | D1: Pág. final | E1: Páginas a imprimir
A2: A | B2: 12 | C2: 2 | D2: 3 | E2: =C2&"–"&D2 -> 2–3
A3: B | B3: 11 | C3: 4 | D3: 5 | E3: =C3&"–"&D3 -> 4–5
A4: C | B4: 11 | C4: 6 | D4: 7 | E4: =C4&"–"&D4 -> 6–7
A5: D | B5: 11 | C5: 8 | D5: 9 | E5: =C5&"–"&D5 -> 8–9
A6: E | B6: 11 | C6: 10 | D6: 11 | E6: =C6&"–"&D6 -> 10–11
A7: Total | B7: =SUM(B2:B6) -> 56
A9: Situaciones en el catálogo | B9: 56
A10: Verificación | B10: =IF(B7=B9,"OK","Revisar") -> OK
A12: Fuente: Lote1_Formularios_lenguaje_real_v2.pdf (11 páginas; la página 1 es la guía del tesista y no se imprime) y situaciones_lote1_v1.csv (56 situaciones: 12 en el formulario A y 11 en cada uno de los demás).

Sheet Listas
A1: Rango de edad | B1: Sí / No | C1: Estado | E1: Definición de los estados
A2: 18–29 | B2: Sí | C2: Pendiente | E2: Pendiente | F2: Aún no se aplicó el formulario.
A3: 30–44 | B3: No | C3: Entregado | E3: Entregado | F3: El formulario se entregó a la persona.
A4: 45–59 | C4: Respondido | E4: Respondido | F4: La persona devolvió la hoja respondida.
A5: 60 a más | C5: Transcrito | E5: Transcrito | F5: Las respuestas ya se pasaron al archivo de la Parte B.

Sheet Notas
A1: Notas de uso, criterios y fuentes
A3: Cómo usar
A4: 1. Asigna a cada persona un código (P01 a P25) que no permita identificarla. El formulario y las páginas a imprimir salen solos en las columnas B y C de la hoja Participantes.
A5: 2. Completa solo las celdas amarillas de Participantes: rango de edad, ocupación, si vive en Juliaca, si hizo un trámite el último año, estado, fecha y observaciones.
A6: 3. Avanza el Estado: Pendiente, Entregado, Respondido y Transcrito (Transcrito = respuestas ya pasadas al archivo de la Parte B).
A7: 4. Cuando alguien deje una situación sin responder, regístrala en la hoja Blancos (código y situación). Las situaciones respondidas de cada persona se calculan solas.
A8: 5. Revisa Resumen y Cobertura. La cobertura se mide por intención (frases reales), no por personas: “Listo para la Parte B” exige participantes transcritos suficientes y todas las intenciones con el mínimo de frases.
A10: Criterios de reclutamiento
A11: • Se usan los cinco formularios (A–E) y cada persona responde uno solo. Cada situación aparece en un solo formulario: omitir uno deja intenciones sin frases reales.
A12: • P01–P20 son la base (4 respuestas por formulario). P21–P25 son reserva: actívalas si los blancos dejan intenciones por debajo de la meta (columna Estado de Cobertura).
A13: • Las personas que reciben el mismo formulario deberían tener edades y ocupaciones distintas (tabla de mezcla de edades en Resumen).
A14: • Las frases las escriben los participantes, no el tesista ni una IA.
... A22: • Los parámetros se pueden cambiar en las celdas amarillas de Resumen. Colores: azul = valor escrito a mano o dato fijo; negro = fórmula; verde = vínculo a otra hoja.
