Workbook

Sheet Sesiones
A1: Registro de sesiones asistidas — piloto exploratorio (datos reales)
A2: Una fila por sesión (SA01, SA02…). Edita solo las celdas amarillas; las columnas Tarjeta 1–3 y las de la derecha (Elegible… Total Likert) son fórmulas. Llena solo con sesiones realizadas: nada de datos de prueba.
A3: Código de sesión | B3: Fecha | C3: Aplicador | D3: Rango de edad | E3: ¿Vive en Juliaca? | F3: ¿Trámite presencial en la MPSR (12 meses)? | G3: Categoría del trámite | H3: Tiempo presencial (rango) | I3: Veces que volvió o hizo seguimiento | J3: Dif.: información no clara (1 = sí) | K3: Dif.: demora excesiva (1 = sí) | L3: Dif.: colas largas (1 = sí) | M3: Dif.: falta de orientación (1 = sí) | N3: Dif.: ninguna (1 = sí) | O3: Dif.: otra (1 = sí) | P3: Pre P7 atención presencial rápida | Q3: Pre P8 resolver dudas sin ir presencialmente | R3: Pre P9 requisitos claros | S3: Pre P10 satisfacción general | T3: Tarjeta 1 | U3: Tarjeta 2 | V3: Tarjeta 3 | W3: Consulta 1: texto escrito | X3: Consulta 1: tiempo hasta respuesta útil (s) | Y3: Consulta 1: mensajes enviados | Z3: Consulta 1: ¿la persona obtuvo lo que necesitaba? | AA3: Consulta 1: ¿respuesta correcta? (aplicador) | AB3: Consulta 1: ¿dijo «no entendí»? | AC3: Consulta 2: texto escrito | AD3: Consulta 2: tiempo hasta respuesta útil (s) | AE3: Consulta 2: mensajes enviados | AF3: Consulta 2: ¿la persona obtuvo lo que necesitaba? | AG3: Consulta 2: ¿respuesta correcta? (aplicador) | AH3: Consulta 2: ¿dijo «no entendí»? | AI3: Consulta 3: texto escrito | AJ3: Consulta 3: tiempo hasta respuesta útil (s) | AK3: Consulta 3: mensajes enviados | AL3: Consulta 3: ¿la persona obtuvo lo que necesitaba? | AM3: Consulta 3: ¿respuesta correcta? (aplicador) | AN3: Consulta 3: ¿dijo «no entendí»? | AO3: Post ítem 1: fácil de usar | AP3: Post ítem 2: tiempo adecuado | AQ3: Post ítem 3: respuestas claras | AR3: Post ítem 4: resolvió mi consulta | AS3: Post ítem 5: confío en la información | AT3: Post ítem 6: prefiero usarlo antes que ir presencialmente | AU3: Post ítem 7: lo usaría de nuevo | AV3: Post ítem 8: lo recomendaría | AW3: Post ítem 9: satisfacción general (pareada con P10) | AX3: Complementaria: tiempo presencial estimado para la consulta 1 | AY3: Incidencias técnicas | AZ3: Elegible y completa | BA3: Minutos pre (línea base) | BB3: Minutos post (promedio de 3 consultas) | BC3: Diferencia post − pre (min) | BD3: % de reducción | BE3: Satisfacción pre (P10) | BF3: Satisfacción post (ítem 9) | BG3: Diferencia de satisfacción | BH3: Consultas con respuesta útil (de 3) | BI3: Consultas correctas (de 3) | BJ3: Consultas con «no entendí» (de 3) | BK3: Total Likert ítems 1–8
A4: SA01 | T4: =INDEX(Tarjetas!$A$4:$A$59,MOD(3*(VALUE(MID(A4,3,2))-1)+0,ROWS(Tarjetas!$A$4:$A$59))+1) -> S01 | U4: =INDEX(Tarjetas!$A$4:$A$59,MOD(3*(VALUE(MID(A4,3,2))-1)+1,ROWS(Tarjetas!$A$4:$A$59))+1) -> S02 | V4: =INDEX(Tarjetas!$A$4:$A$59,MOD(3*(VALUE(MID(A4,3,2))-1)+2,ROWS(Tarjetas!$A$4:$A$59))+1) -> S03 | AZ4: =IF(COUNTA(B4,F4)=0,"",IF(AND(F4="Sí",H4<>"",S4<>"",COUNT(X4,AD4,AJ4)=3,COUNT(AO4:AV4)=8,AW4<>""),"Sí","No")) | BA4: =IF(H4="","",IFERROR(INDEX(Parametros!$B$4:$B$9,MATCH(H4,Parametros!$A$4:$A$9,0)),"")) | BB4: =IF(COUNT(X4,AD4,AJ4)=3,AVERAGE(X4,AD4,AJ4)/60,"") | BC4: =IF(AND(ISNUMBER(BA4),ISNUMBER(BB4)),BB4-BA4,"") | BD4: =IF(AND(ISNUMBER(BA4),ISNUMBER(BB4)),IF(BA4>0,(BA4-BB4)/BA4,""),"") | BE4: =IF(S4="","",S4) | BF4: =IF(AW4="","",AW4) | BG4: =IF(AND(ISNUMBER(BE4),ISNUMBER(BF4)),BF4-BE4,"") | BH4: =IF(COUNTA(Z4,AF4,AL4)=0,"",(Z4="Sí")+(AF4="Sí")+(AL4="Sí")) | BI4: =IF(COUNTA(AA4,AG4,AM4)=0,"",(AA4="Sí")+(AG4="Sí")+(AM4="Sí")) | BJ4: =IF(COUNTA(AB4,AH4,AN4)=0,"",(AB4="Sí")+(AH4="Sí")+(AN4="Sí")) | BK4: =IF(COUNT(AO4:AV4)=8,SUM(AO4:AV4),"")
A5: SA02 | T5: =INDEX(Tarjetas!$A$4:$A$59,MOD(3*(VALUE(MID(A5,3,2))-1)+0,ROWS(Tarjetas!$A$4:$A$59))+1) -> S04 | U5: =INDEX(Tarjetas!$A$4:$A$59,MOD(3*(VALUE(MID(A5,3,2))-1)+1,ROWS(Tarjetas!$A$4:$A$59))+1) -> S05 | V5: =INDEX(Tarjetas!$A$4:$A$59,MOD(3*(VALUE(MID(A5,3,2))-1)+2,ROWS(Tarjetas!$A$4:$A$59))+1) -> S06 | AZ5: =IF(COUNTA(B5,F5)=0,"",IF(AND(F5="Sí",H5<>"",S5<>"",COUNT(X5,AD5,AJ5)=3,COUNT(AO5:AV5)=8,AW5<>""),"Sí","No")) | BA5: =IF(H5="","",IFERROR(INDEX(Parametros!$B$4:$B$9,MATCH(H5,Parametros!$A$4:$A$9,0)),"")) | BB5: =IF(COUNT(X5,AD5,AJ5)=3,AVERAGE(X5,AD5,AJ5)/60,"") | BC5: =IF(AND(ISNUMBER(BA5),ISNUMBER(BB5)),BB5-BA5,"") | BD5: =IF(AND(ISNUMBER(BA5),ISNUMBER(BB5)),IF(BA5>0,(BA5-BB5)/BA5,""),"") | BE5: =IF(S5="","",S5) | BF5: =IF(AW5="","",AW5) | BG5: =IF(AND(ISNUMBER(BE5),ISNUMBER(BF5)),BF5-BE5,"") | BH5: =IF(COUNTA(Z5,AF5,AL5)=0,"",(Z5="Sí")+(AF5="Sí")+(AL5="Sí")) | BI5: =IF(COUNTA(AA5,AG5,AM5)=0,"",(AA5="Sí")+(AG5="Sí")+(AM5="Sí")) | BJ5: =IF(COUNTA(AB5,AH5,AN5)=0,"",(AB5="Sí")+(AH5="Sí")+(AN5="Sí")) | BK5: =IF(COUNT(AO5:AV5)=8,SUM(AO5:AV5),"")
A6: SA03 | T6: =INDEX(Tarjetas!$A$4:$A$59,MOD(3*(VALUE(MID(A6,3,2))-1)+0,ROWS(Tarjetas!$A$4:$A$59))+1) -> S07 | U6: =INDEX(Tarjetas!$A$4:$A$59,MOD(3*(VALUE(MID(A6,3,2))-1)+1,ROWS(Tarjetas!$A$4:$A$59))+1) -> S08 | V6: =INDEX(Tarjetas!$A$4:$A$59,MOD(3*(VALUE(MID(A6,3,2))-1)+2,ROWS(Tarjetas!$A$4:$A$59))+1) -> S09 | AZ6: =IF(COUNTA(B6,F6)=0,"",IF(AND(F6="Sí",H6<>"",S6<>"",COUNT(X6,AD6,AJ6)=3,COUNT(AO6:AV6)=8,AW6<>""),"Sí","No")) | BA6: =IF(H6="","",IFERROR(INDEX(Parametros!$B$4:$B$9,MATCH(H6,Parametros!$A$4:$A$9,0)),"")) | BB6: =IF(COUNT(X6,AD6,AJ6)=3,AVERAGE(X6,AD6,AJ6)/60,"") | BC6: =IF(AND(ISNUMBER(BA6),ISNUMBER(BB6)),BB6-BA6,"") | BD6: =IF(AND(ISNUMBER(BA6),ISNUMBER(BB6)),IF(BA6>0,(BA6-BB6)/BA6,""),"") | BE6: =IF(S6="","",S6) | BF6: =IF(AW6="","",AW6) | BG6: =IF(AND(ISNUMBER(BE6),ISNUMBER(BF6)),BF6-BE6,"") | BH6: =IF(COUNTA(Z6,AF6,AL6)=0,"",(Z6="Sí")+(AF6="Sí")+(AL6="Sí")) | BI6: =IF(COUNTA(AA6,AG6,AM6)=0,"",(AA6="Sí")+(AG6="Sí")+(AM6="Sí")) | BJ6: =IF(COUNTA(AB6,AH6,AN6)=0,"",(AB6="Sí")+(AH6="Sí")+(AN6="Sí")) | BK6: =IF(COUNT(AO6:AV6)=8,SUM(AO6:AV6),"")
A7: SA04 | T7: =INDEX(Tarjetas!$A$4:$A$59,MOD(3*(VALUE(MID(A7,3,2))-1)+0,ROWS(Tarjetas!$A$4:$A$59))+1) -> S10 | U7: =INDEX(Tarjetas!$A$4:$A$59,MOD(3*(VALUE(MID(A7,3,2))-1)+1,ROWS(Tarjetas!$A$4:$A$59))+1) -> S11 | V7: =INDEX(Tarjetas!$A$4:$A$59,MOD(3*(VALUE(MID(A7,3,2))-1)+2,ROWS(Tarjetas!$A$4:$A$59))+1) -> S12 | AZ7: =IF(COUNTA(B7,F7)=0,"",IF(AND(F7="Sí",H7<>"",S7<>"",COUNT(X7,AD7,AJ7)=3,COUNT(AO7:AV7)=8,AW7<>""),"Sí","No")) | BA7: =IF(H7="","",IFERROR(INDEX(Parametros!$B$4:$B$9,MATCH(H7,Parametros!$A$4:$A$9,0)),"")) | BB7: =IF(COUNT(X7,AD7,AJ7)=3,AVERAGE(X7,AD7,AJ7)/60,"") | BC7: =IF(AND(ISNUMBER(BA7),ISNUMBER(BB7)),BB7-BA7,"") | BD7: =IF(AND(ISNUMBER(BA7),ISNUMBER(BB7)),IF(BA7>0,(BA7-BB7)/BA7,""),"") | BE7: =IF(S7="","",S7) | BF7: =IF(AW7="","",AW7) | BG7: =IF(AND(ISNUMBER(BE7),ISNUMBER(BF7)),BF7-BE7,"") | BH7: =IF(COUNTA(Z7,AF7,AL7)=0,"",(Z7="Sí")+(AF7="Sí")+(AL7="Sí")) | BI7: =IF(COUNTA(AA7,AG7,AM7)=0,"",(AA7="Sí")+(AG7="Sí")+(AM7="Sí")) | BJ7: =IF(COUNTA(AB7,AH7,AN7)=0,"",(AB7="Sí")+(AH7="Sí")+(AN7="Sí")) | BK7: =IF(COUNT(AO7:AV7)=8,SUM(AO7:AV7),"")
A8: SA05 | T8: =INDEX(Tarjetas!$A$4:$A$59,MOD(3*(VALUE(MID(A8,3,2))-1)+0,ROWS(Tarjetas!$A$4:$A$59))+1) -> S13 | U8: =INDEX(Tarjetas!$A$4:$A$59,MOD(3*(VALUE(MID(A8,3,2))-1)+1,ROWS(Tarjetas!$A$4:$A$59))+1) -> S14 | V8: =INDEX(Tarjetas!$A$4:$A$59,MOD(3*(VALUE(MID(A8,3,2))-1)+2,ROWS(Tarjetas!$A$4:$A$59))+1) -> S15 | AZ8: =IF(COUNTA(B8,F8)=0,"",IF(AND(F8="Sí",H8<>"",S8<>"",COUNT(X8,AD8,AJ8)=3,COUNT(AO8:AV8)=8,AW8<>""),"Sí","No")) | BA8: =IF(H8="","",IFERROR(INDEX(Parametros!$B$4:$B$9,MATCH(H8,Parametros!$A$4:$A$9,0)),"")) | BB8: =IF(COUNT(X8,AD8,AJ8)=3,AVERAGE(X8,AD8,AJ8)/60,"") | BC8: =IF(AND(ISNUMBER(BA8),ISNUMBER(BB8)),BB8-BA8,"") | BD8: =IF(AND(ISNUMBER(BA8),ISNUMBER(BB8)),IF(BA8>0,(BA8-BB8)/BA8,""),"") | BE8: =IF(S8="","",S8) | BF8: =IF(AW8="","",AW8) | BG8: =IF(AND(ISNUMBER(BE8),ISNUMBER(BF8)),BF8-BE8,"") | BH8: =IF(COUNTA(Z8,AF8,AL8)=0,"",(Z8="Sí")+(AF8="Sí")+(AL8="Sí")) | BI8: =IF(COUNTA(AA8,AG8,AM8)=0,"",(AA8="Sí")+(AG8="Sí")+(AM8="Sí")) | BJ8: =IF(COUNTA(AB8,AH8,AN8)=0,"",(AB8="Sí")+(AH8="Sí")+(AN8="Sí")) | BK8: =IF(COUNT(AO8:AV8)=8,SUM(AO8:AV8),"")
A9: SA06 | T9: =INDEX(Tarjetas!$A$4:$A$59,MOD(3*(VALUE(MID(A9,3,2))-1)+0,ROWS(Tarjetas!$A$4:$A$59))+1) -> S16 | U9: =INDEX(Tarjetas!$A$4:$A$59,MOD(3*(VALUE(MID(A9,3,2))-1)+1,ROWS(Tarjetas!$A$4:$A$59))+1) -> S17 | V9: =INDEX(Tarjetas!$A$4:$A$59,MOD(3*(VALUE(MID(A9,3,2))-1)+2,ROWS(Tarjetas!$A$4:$A$59))+1) -> S18 | AZ9: =IF(COUNTA(B9,F9)=0,"",IF(AND(F9="Sí",H9<>"",S9<>"",COUNT(X9,AD9,AJ9)=3,COUNT(AO9:AV9)=8,AW9<>""),"Sí","No")) | BA9: =IF(H9="","",IFERROR(INDEX(Parametros!$B$4:$B$9,MATCH(H9,Parametros!$A$4:$A$9,0)),"")) | BB9: =IF(COUNT(X9,AD9,AJ9)=3,AVERAGE(X9,AD9,AJ9)/60,"") | BC9: =IF(AND(ISNUMBER(BA9),ISNUMBER(BB9)),BB9-BA9,"") | BD9: =IF(AND(ISNUMBER(BA9),ISNUMBER(BB9)),IF(BA9>0,(BA9-BB9)/BA9,""),"") | BE9: =IF(S9="","",S9) | BF9: =IF(AW9="","",AW9) | BG9: =IF(AND(ISNUMBER(BE9),ISNUMBER(BF9)),BF9-BE9,"") | BH9: =IF(COUNTA(Z9,AF9,AL9)=0,"",(Z9="Sí")+(AF9="Sí")+(AL9="Sí")) | BI9: =IF(COUNTA(AA9,AG9,AM9)=0,"",(AA9="Sí")+(AG9="Sí")+(AM9="Sí")) | BJ9: =IF(COUNTA(AB9,AH9,AN9)=0,"",(AB9="Sí")+(AH9="Sí")+(AN9="Sí")) | BK9: =IF(COUNT(AO9:AV9)=8,SUM(AO9:AV9),"")
A10: SA07 | T10: =INDEX(Tarjetas!$A$4:$A$59,MOD(3*(VALUE(MID(A10,3,2))-1)+0,ROWS(Tarjetas!$A$4:$A$59))+1) -> S19 | U10: =INDEX(Tarjetas!$A$4:$A$59,MOD(3*(VALUE(MID(A10,3,2))-1)+1,ROWS(Tarjetas!$A$4:$A$59))+1) -> S20 | V10: =INDEX(Tarjetas!$A$4:$A$59,MOD(3*(VALUE(MID(A10,3,2))-1)+2,ROWS(Tarjetas!$A$4:$A$59))+1) -> S21 | AZ10: =IF(COUNTA(B10,F10)=0,"",IF(AND(F10="Sí",H10<>"",S10<>"",COUNT(X10,AD10,AJ10)=3,COUNT(AO10:AV10)=8,AW10<>""),"Sí","No")) | BA10: =IF(H10="","",IFERROR(INDEX(Parametros!$B$4:$B$9,MATCH(H10,Parametros!$A$4:$A$9,0)),"")) | BB10: =IF(COUNT(X10,AD10,AJ10)=3,AVERAGE(X10,AD10,AJ10)/60,"") | BC10: =IF(AND(ISNUMBER(BA10),ISNUMBER(BB10)),BB10-BA10,"") | BD10: =IF(AND(ISNUMBER(BA10),ISNUMBER(BB10)),IF(BA10>0,(BA10-BB10)/BA10,""),"") | BE10: =IF(S10="","",S10) | BF10: =IF(AW10="","",AW10) | BG10: =IF(AND(ISNUMBER(BE10),ISNUMBER(BF10)),BF10-BE10,"") | BH10: =IF(COUNTA(Z10,AF10,AL10)=0,"",(Z10="Sí")+(AF10="Sí")+(AL10="Sí")) | BI10: =IF(COUNTA(AA10,AG10,AM10)=0,"",(AA10="Sí")+(AG10="Sí")+(AM10="Sí")) | BJ10: =IF(COUNTA(AB10,AH10,AN10)=0,"",(AB10="Sí")+(AH10="Sí")+(AN10="Sí")) | BK10: =IF(COUNT(AO10:AV10)=8,SUM(AO10:AV10),"")
A11: SA08 | T11: =INDEX(Tarjetas!$A$4:$A$59,MOD(3*(VALUE(MID(A11,3,2))-1)+0,ROWS(Tarjetas!$A$4:$A$59))+1) -> S22 | U11: =INDEX(Tarjetas!$A$4:$A$59,MOD(3*(VALUE(MID(A11,3,2))-1)+1,ROWS(Tarjetas!$A$4:$A$59))+1) -> S23 | V11: =INDEX(Tarjetas!$A$4:$A$59,MOD(3*(VALUE(MID(A11,3,2))-1)+2,ROWS(Tarjetas!$A$4:$A$59))+1) -> S24 | AZ11: =IF(COUNTA(B11,F11)=0,"",IF(AND(F11="Sí",H11<>"",S11<>"",COUNT(X11,AD11,AJ11)=3,COUNT(AO11:AV11)=8,AW11<>""),"Sí","No")) | BA11: =IF(H11="","",IFERROR(INDEX(Parametros!$B$4:$B$9,MATCH(H11,Parametros!$A$4:$A$9,0)),"")) | BB11: =IF(COUNT(X11,AD11,AJ11)=3,AVERAGE(X11,AD11,AJ11)/60,"") | BC11: =IF(AND(ISNUMBER(BA11),ISNUMBER(BB11)),BB11-BA11,"") | BD11: =IF(AND(ISNUMBER(BA11),ISNUMBER(BB11)),IF(BA11>0,(BA11-BB11)/BA11,""),"") | BE11: =IF(S11="","",S11) | BF11: =IF(AW11="","",AW11) | BG11: =IF(AND(ISNUMBER(BE11),ISNUMBER(BF11)),BF11-BE11,"") | BH11: =IF(COUNTA(Z11,AF11,AL11)=0,"",(Z11="Sí")+(AF11="Sí")+(AL11="Sí")) | BI11: =IF(COUNTA(AA11,AG11,AM11)=0,"",(AA11="Sí")+(AG11="Sí")+(AM11="Sí")) | BJ11: =IF(COUNTA(AB11,AH11,AN11)=0,"",(AB11="Sí")+(AH11="Sí")+(AN11="Sí")) | BK11: =IF(COUNT(AO11:AV11)=8,SUM(AO11:AV11),"")
A12: SA09 | T12: =INDEX(Tarjetas!$A$4:$A$59,MOD(3*(VALUE(MID(A12,3,2))-1)+0,ROWS(Tarjetas!$A$4:$A$59))+1) -> S25 | U12: =INDEX(Tarjetas!$A$4:$A$59,MOD(3*(VALUE(MID(A12,3,2))-1)+1,ROWS(Tarjetas!$A$4:$A$59))+1) -> S26 | V12: =INDEX(Tarjetas!$A$4:$A$59,MOD(3*(VALUE(MID(A12,3,2))-1)+2,ROWS(Tarjetas!$A$4:$A$59))+1) -> S27 | AZ12: =IF(COUNTA(B12,F12)=0,"",IF(AND(F12="Sí",H12<>"",S12<>"",COUNT(X12,AD12,AJ12)=3,COUNT(AO12:AV12)=8,AW12<>""),"Sí","No")) | BA12: =IF(H12="","",IFERROR(INDEX(Parametros!$B$4:$B$9,MATCH(H12,Parametros!$A$4:$A$9,0)),"")) | BB12: =IF(COUNT(X12,AD12,AJ12)=3,AVERAGE(X12,AD12,AJ12)/60,"") | BC12: =IF(AND(ISNUMBER(BA12),ISNUMBER(BB12)),BB12-BA12,"") | BD12: =IF(AND(ISNUMBER(BA12),ISNUMBER(BB12)),IF(BA12>0,(BA12-BB12)/BA12,""),"") | BE12: =IF(S12="","",S12) | BF12: =IF(AW12="","",AW12) | BG12: =IF(AND(ISNUMBER(BE12),ISNUMBER(BF12)),BF12-BE12,"") | BH12: =IF(COUNTA(Z12,AF12,AL12)=0,"",(Z12="Sí")+(AF12="Sí")+(AL12="Sí")) | BI12: =IF(COUNTA(AA12,AG12,AM12)=0,"",(AA12="Sí")+(AG12="Sí")+(AM12="Sí")) | BJ12: =IF(COUNTA(AB12,AH12,AN12)=0,"",(AB12="Sí")+(AH12="Sí")+(AN12="Sí")) | BK12: =IF(COUNT(AO12:AV12)=8,SUM(AO12:AV12),"")
A13: SA10 | T13: =INDEX(Tarjetas!$A$4:$A$59,MOD(3*(VALUE(MID(A13,3,2))-1)+0,ROWS(Tarjetas!$A$4:$A$59))+1) -> S28 | U13: =INDEX(Tarjetas!$A$4:$A$59,MOD(3*(VALUE(MID(A13,3,2))-1)+1,ROWS(Tarjetas!$A$4:$A$59))+1) -> S29 | V13: =INDEX(Tarjetas!$A$4:$A$59,MOD(3*(VALUE(MID(A13,3,2))-1)+2,ROWS(Tarjetas!$A$4:$A$59))+1) -> S30 | AZ13: =IF(COUNTA(B13,F13)=0,"",IF(AND(F13="Sí",H13<>"",S13<>"",COUNT(X13,AD13,AJ13)=3,COUNT(AO13:AV13)=8,AW13<>""),"Sí","No")) | BA13: =IF(H13="","",IFERROR(INDEX(Parametros!$B$4:$B$9,MATCH(H13,Parametros!$A$4:$A$9,0)),"")) | BB13: =IF(COUNT(X13,AD13,AJ13)=3,AVERAGE(X13,AD13,AJ13)/60,"") | BC13: =IF(AND(ISNUMBER(BA13),ISNUMBER(BB13)),BB13-BA13,"") | BD13: =IF(AND(ISNUMBER(BA13),ISNUMBER(BB13)),IF(BA13>0,(BA13-BB13)/BA13,""),"") | BE13: =IF(S13="","",S13) | BF13: =IF(AW13="","",AW13) | BG13: =IF(AND(ISNUMBER(BE13),ISNUMBER(BF13)),BF13-BE13,"") | BH13: =IF(COUNTA(Z13,AF13,AL13)=0,"",(Z13="Sí")+(AF13="Sí")+(AL13="Sí")) | BI13: =IF(COUNTA(AA13,AG13,AM13)=0,"",(AA13="Sí")+(AG13="Sí")+(AM13="Sí")) | BJ13: =IF(COUNTA(AB13,AH13,AN13)=0,"",(AB13="Sí")+(AH13="Sí")+(AN13="Sí")) | BK13: =IF(COUNT(AO13:AV13)=8,SUM(AO13:AV13),"")
A14: SA11 | T14: =INDEX(Tarjetas!$A$4:$A$59,MOD(3*(VALUE(MID(A14,3,2))-1)+0,ROWS(Tarjetas!$A$4:$A$59))+1) -> S31 | U14: =INDEX(Tarjetas!$A$4:$A$59,MOD(3*(VALUE(MID(A14,3,2))-1)+1,ROWS(Tarjetas!$A$4:$A$59))+1) -> S32 | V14: =INDEX(Tarjetas!$A$4:$A$59,MOD(3*(VALUE(MID(A14,3,2))-1)+2,ROWS(Tarjetas!$A$4:$A$59))+1) -> S33 | AZ14: =IF(COUNTA(B14,F14)=0,"",IF(AND(F14="Sí",H14<>"",S14<>"",COUNT(X14,AD14,AJ14)=3,COUNT(AO14:AV14)=8,AW14<>""),"Sí","No")) | BA14: =IF(H14="","",IFERROR(INDEX(Parametros!$B$4:$B$9,MATCH(H14,Parametros!$A$4:$A$9,0)),"")) | BB14: =IF(COUNT(X14,AD14,AJ14)=3,AVERAGE(X14,AD14,AJ14)/60,"") | BC14: =IF(AND(ISNUMBER(BA14),ISNUMBER(BB14)),BB14-BA14,"") | BD14: =IF(AND(ISNUMBER(BA14),ISNUMBER(BB14)),IF(BA14>0,(BA14-BB14)/BA14,""),"") | BE14: =IF(S14="","",S14) | BF14: =IF(AW14="","",AW14) | BG14: =IF(AND(ISNUMBER(BE14),ISNUMBER(BF14)),BF14-BE14,"") | BH14: =IF(COUNTA(Z14,AF14,AL14)=0,"",(Z14="Sí")+(AF14="Sí")+(AL14="Sí")) | BI14: =IF(COUNTA(AA14,AG14,AM14)=0,"",(AA14="Sí")+(AG14="Sí")+(AM14="Sí")) | BJ14: =IF(COUNTA(AB14,AH14,AN14)=0,"",(AB14="Sí")+(AH14="Sí")+(AN14="Sí")) | BK14: =IF(COUNT(AO14:AV14)=8,SUM(AO14:AV14),"")
A15: SA12 | T15: =INDEX(Tarjetas!$A$4:$A$59,MOD(3*(VALUE(MID(A15,3,2))-1)+0,ROWS(Tarjetas!$A$4:$A$59))+1) -> S34 | U15: =INDEX(Tarjetas!$A$4:$A$59,MOD(3*(VALUE(MID(A15,3,2))-1)+1,ROWS(Tarjetas!$A$4:$A$59))+1) -> S35 | V15: =INDEX(Tarjetas!$A$4:$A$59,MOD(3*(VALUE(MID(A15,3,2))-1)+2,ROWS(Tarjetas!$A$4:$A$59))+1) -> S36 | AZ15: =IF(COUNTA(B15,F15)=0,"",IF(AND(F15="Sí",H15<>"",S15<>"",COUNT(X15,AD15,AJ15)=3,COUNT(AO15:AV15)=8,AW15<>""),"Sí","No")) | BA15: =IF(H15="","",IFERROR(INDEX(Parametros!$B$4:$B$9,MATCH(H15,Parametros!$A$4:$A$9,0)),"")) | BB15: =IF(COUNT(X15,AD15,AJ15)=3,AVERAGE(X15,AD15,AJ15)/60,"") | BC15: =IF(AND(ISNUMBER(BA15),ISNUMBER(BB15)),BB15-BA15,"") | BD15: =IF(AND(ISNUMBER(BA15),ISNUMBER(BB15)),IF(BA15>0,(BA15-BB15)/BA15,""),"") | BE15: =IF(S15="","",S15) | BF15: =IF(AW15="","",AW15) | BG15: =IF(AND(ISNUMBER(BE15),ISNUMBER(BF15)),BF15-BE15,"") | BH15: =IF(COUNTA(Z15,AF15,AL15)=0,"",(Z15="Sí")+(AF15="Sí")+(AL15="Sí")) | BI15: =IF(COUNTA(AA15,AG15,AM15)=0,"",(AA15="Sí")+(AG15="Sí")+(AM15="Sí")) | BJ15: =IF(COUNTA(AB15,AH15,AN15)=0,"",(AB15="Sí")+(AH15="Sí")+(AN15="Sí")) | BK15: =IF(COUNT(AO15:AV15)=8,SUM(AO15:AV15),"")
... A78: SA75 | T78: =INDEX(Tarjetas!$A$4:$A$59,MOD(3*(VALUE(MID(A78,3,2))-1)+0,ROWS(Tarjetas!$A$4:$A$59))+1) -> S55 | U78: =INDEX(Tarjetas!$A$4:$A$59,MOD(3*(VALUE(MID(A78,3,2))-1)+1,ROWS(Tarjetas!$A$4:$A$59))+1) -> S56 | V78: =INDEX(Tarjetas!$A$4:$A$59,MOD(3*(VALUE(MID(A78,3,2))-1)+2,ROWS(Tarjetas!$A$4:$A$59))+1) -> S01 | AZ78: =IF(COUNTA(B78,F78)=0,"",IF(AND(F78="Sí",H78<>"",S78<>"",COUNT(X78,AD78,AJ78)=3,COUNT(AO78:AV78)=8,AW78<>""),"Sí","No")) | BA78: =IF(H78="","",IFERROR(INDEX(Parametros!$B$4:$B$9,MATCH(H78,Parametros!$A$4:$A$9,0)),"")) | BB78: =IF(COUNT(X78,AD78,AJ78)=3,AVERAGE(X78,AD78,AJ78)/60,"") | BC78: =IF(AND(ISNUMBER(BA78),ISNUMBER(BB78)),BB78-BA78,"") | BD78: =IF(AND(ISNUMBER(BA78),ISNUMBER(BB78)),IF(BA78>0,(BA78-BB78)/BA78,""),"") | BE78: =IF(S78="","",S78) | BF78: =IF(AW78="","",AW78) | BG78: =IF(AND(ISNUMBER(BE78),ISNUMBER(BF78)),BF78-BE78,"") | BH78: =IF(COUNTA(Z78,AF78,AL78)=0,"",(Z78="Sí")+(AF78="Sí")+(AL78="Sí")) | BI78: =IF(COUNTA(AA78,AG78,AM78)=0,"",(AA78="Sí")+(AG78="Sí")+(AM78="Sí")) | BJ78: =IF(COUNTA(AB78,AH78,AN78)=0,"",(AB78="Sí")+(AH78="Sí")+(AN78="Sí")) | BK78: =IF(COUNT(AO78:AV78)=8,SUM(AO78:AV78),"")
A80: Ejemplo de fila completada (solo muestra el formato; no cuenta en ningún cálculo):
A81: EJ01 | B81: 46307 | C81: Tesista | D81: 30–44 | E81: Sí | F81: Sí | G81: Licencias y autorizaciones | H81: 1–2 horas | I81: 1 vez | J81: 1 | K81: 1 | L81: 0 | M81: 0 | N81: 0 | O81: 0 | P81: 2 | Q81: 2 | R81: 3 | S81: 3 | T81: S01 | U81: S02 | V81: S03 | W81: Qué papeles piden para abrir una tienda | X81: 42 | Y81: 1 | Z81: Sí | AA81: Sí | AB81: No | AC81: Cuánto cuesta el permiso | AD81: 65 | AE81: 2 | AF81: Sí | AG81: Parcial | AH81: No | AI81: En cuánto tiempo me lo dan | AJ81: 180 | AK81: 3 | AL81: No | AM81: No | AN81: Sí | AO81: 4 | AP81: 5 | AQ81: 4 | AR81: 3 | AS81: 4 | AT81: 3 | AU81: 4 | AV81: 4 | AW81: 4 | AX81: 1–2 horas | AY81: Ninguna | AZ81: Sí | BA81: 90 | BB81: 1.6 | BC81: -88.4 | BD81: 0.98228395 | BE81: 3 | BF81: 4 | BG81: 1 | BH81: 2 | BI81: 1 | BJ81: 1 | BK81: 31

Sheet Resumen
A1: Resumen del piloto exploratorio (sesión asistida)
A2: Todo son fórmulas sobre la hoja Sesiones, solo con sesiones elegibles y completas. La prueba de hipótesis (Shapiro-Wilk, luego t pareada o Wilcoxon) se corre con el script de análisis; esta hoja solo resume.
A4: Avance
A5: Sesiones registradas | B5: =COUNTA(Sesiones!$B$4:$B$78) -> 0
A6: Sesiones elegibles y completas | B6: =COUNTIF(Sesiones!$AZ$4:$AZ$78,"Sí") -> 0
A7: No elegibles (sin trámite presencial en 12 meses) | B7: =COUNTIF(Sesiones!$F$4:$F$78,"No") -> 0
A8: Incompletas (elegibles con datos faltantes) | B8: =COUNTIFS(Sesiones!$F$4:$F$78,"Sí",Sesiones!$AZ$4:$AZ$78,"No") -> 0 | C8: Completa los datos faltantes o reemplaza la sesión.
A9: Meta de sesiones | B9: =Parametros!$B$14 -> 60
A10: Faltan | B10: =MAX(0,B9-B6) -> 60
A11: Estado | B11: =IF(B6>=B9,"Meta alcanzada",IF(B6>0,"Parcial (n = "&B6&")","Sin datos")) -> Sin datos | C11: Si no se llega a la meta, el piloto se presenta con el n real y se declara.
A13: Tiempo (OE3) — línea base recordada frente a prueba con el asistente
A14: Tiempo medio presencial (línea base recordada), minutos | B14: =IFERROR(AVERAGEIFS(Sesiones!$BA$4:$BA$78,Sesiones!$AZ$4:$AZ$78,"Sí"),"") | C14: Punto medio de cada rango (hoja Parametros).
A15: Tiempo medio con el asistente, minutos | B15: =IFERROR(AVERAGEIFS(Sesiones!$BB$4:$BB$78,Sesiones!$AZ$4:$AZ$78,"Sí"),"") | C15: Promedio de las 3 consultas por persona, en minutos.
A16: Reducción del tiempo medio | B16: =IFERROR((B14-B15)/B14,"") | C16: =IF(B16="","","Meta ≥ "&TEXT(Parametros!$B$15,"0%")&": "&IF(B16>=Parametros!$B$15,"cumple","no cumple"))
A17: Reducción media individual | B17: =IFERROR(AVERAGEIFS(Sesiones!$BD$4:$BD$78,Sesiones!$AZ$4:$AZ$78,"Sí"),"") | C17: Promedio de los porcentajes de cada persona.
A19: Satisfacción (OE4)
A20: Satisfacción previa con la atención presencial (P10), media | B20: =IFERROR(AVERAGEIFS(Sesiones!$BE$4:$BE$78,Sesiones!$AZ$4:$AZ$78,"Sí"),"")
A21: Satisfacción con el asistente (ítem 9), media | B21: =IFERROR(AVERAGEIFS(Sesiones!$BF$4:$BF$78,Sesiones!$AZ$4:$AZ$78,"Sí"),"")
A22: Diferencia media (post − pre) | B22: =IFERROR(B21-B20,"")
A23: Media de los ítems 1–8 del asistente | B23: =IFERROR(AVERAGEIFS(Sesiones!$BK$4:$BK$78,Sesiones!$AZ$4:$AZ$78,"Sí")/COLUMNS(Calc!$B$3:$I$3),"") | C23: =IF(B23="","","Meta ≥ "&TEXT(Parametros!$B$16,"0.0")&": "&IF(B23>=Parametros!$B$16,"cumple","no cumple"))
A24: Alfa de Cronbach (ítems 1–8) | B24: =IFERROR((COLUMNS(Calc!$B$3:$I$3)/(COLUMNS(Calc!$B$3:$I$3)-1))*(1-(VAR(Calc!B4:B78)+VAR(Calc!C4:C78)+VAR(Calc!D4:D78)+VAR(Calc!E4:E78)+VAR(Calc!F4:F78)+VAR(Calc!G4:G78)+VAR(Calc!H4:H78)+VAR(Calc!I4:I78))/VAR(Calc!$J$4:$J$78)),"") | C24: =IF(B24="","","Mínimo "&TEXT(Parametros!$B$17,"0.00")&": "&IF(B24>=Parametros!$B$17,"cumple","no cumple"))
A26: Desempeño del asistente en las consultas
A27: Consultas registradas (sesiones elegibles) | B27: =3*B6 -> 0
A28: Respuesta útil según la persona | B28: =IFERROR(SUMIFS(Sesiones!$BH$4:$BH$78,Sesiones!$AZ$4:$AZ$78,"Sí")/B27,"")
A29: Respuesta correcta según el aplicador | B29: =IFERROR(SUMIFS(Sesiones!$BI$4:$BI$78,Sesiones!$AZ$4:$AZ$78,"Sí")/B27,"") | C29: «Sí» solamente; las «Parcial» no se cuentan.
A30: Consultas con «no entendí» | B30: =IFERROR(SUMIFS(Sesiones!$BJ$4:$BJ$78,Sesiones!$AZ$4:$AZ$78,"Sí")/B27,"")
A31: Mensajes promedio por consulta | B31: =IFERROR((SUMIFS(Sesiones!$Y$4:$Y$78,Sesiones!$AZ$4:$AZ$78,"Sí")+SUMIFS(Sesiones!$AE$4:$AE$78,Sesiones!$AZ$4:$AZ$78,"Sí")+SUMIFS(Sesiones!$AK$4:$AK$78,Sesiones!$AZ$4:$AZ$78,"Sí"))/B27,"")
A32: Mínimo de consultas por tarjeta | B32: =MIN(Tarjetas!$D$4:$D$59) -> 0 | C32: Con 60 sesiones elegibles cada tarjeta debería tener 3 o más.

Sheet Tarjetas
A1: Tarjetas de situación (catálogo)
A2: Las 56 situaciones del catálogo situaciones_lote1_v1.csv y la intención esperada de cada una. Cada código de sesión recibe 3 tarjetas fijas (hoja Sesiones, columnas Tarjeta 1–3). La columna D cuenta las consultas ya registradas de sesiones elegibles.
A3: Tarjeta | B3: Intención esperada | C3: Texto de la situación | D3: Consultas registradas (sesiones elegibles)
A4: S01 | B4: licencia_funcionamiento_requisitos | C4: Vas a abrir una tiendita en tu barrio y no sabes qué papeles te van a pedir en la municipalidad para poder atender legalmente. | D4: =COUNTIFS(Sesiones!$T$4:$T$78,A4,Sesiones!$AZ$4:$AZ$78,"Sí")+COUNTIFS(Sesiones!$U$4:$U$78,A4,Sesiones!$AZ$4:$AZ$78,"Sí")+COUNTIFS(Sesiones!$V$4:$V$78,A4,Sesiones!$AZ$4:$AZ$78,"Sí") -> 0
A5: S02 | B5: licencia_funcionamiento_costo | C5: Ya sabes que necesitas un permiso de la municipalidad para tu negocio y quieres saber cuánto tendrías que pagar por él. | D5: =COUNTIFS(Sesiones!$T$4:$T$78,A5,Sesiones!$AZ$4:$AZ$78,"Sí")+COUNTIFS(Sesiones!$U$4:$U$78,A5,Sesiones!$AZ$4:$AZ$78,"Sí")+COUNTIFS(Sesiones!$V$4:$V$78,A5,Sesiones!$AZ$4:$AZ$78,"Sí") -> 0
A6: S03 | B6: licencia_funcionamiento_plazo | C6: Entregaste tus papeles para el permiso de tu negocio y quieres saber cuántos días demoran en dártelo. | D6: =COUNTIFS(Sesiones!$T$4:$T$78,A6,Sesiones!$AZ$4:$AZ$78,"Sí")+COUNTIFS(Sesiones!$U$4:$U$78,A6,Sesiones!$AZ$4:$AZ$78,"Sí")+COUNTIFS(Sesiones!$V$4:$V$78,A6,Sesiones!$AZ$4:$AZ$78,"Sí") -> 0
A7: S04 | B7: licencia_edificacion_requisitos | C7: Quieres construir un segundo piso en tu casa y quieres saber qué documentos tendrías que presentar antes de empezar la obra. | D7: =COUNTIFS(Sesiones!$T$4:$T$78,A7,Sesiones!$AZ$4:$AZ$78,"Sí")+COUNTIFS(Sesiones!$U$4:$U$78,A7,Sesiones!$AZ$4:$AZ$78,"Sí")+COUNTIFS(Sesiones!$V$4:$V$78,A7,Sesiones!$AZ$4:$AZ$78,"Sí") -> 0
A8: S05 | B8: licencia_edificacion_costo | C8: Vas a construir en tu terreno y quieres saber cuánto cobra la municipalidad por autorizar la obra. | D8: =COUNTIFS(Sesiones!$T$4:$T$78,A8,Sesiones!$AZ$4:$AZ$78,"Sí")+COUNTIFS(Sesiones!$U$4:$U$78,A8,Sesiones!$AZ$4:$AZ$78,"Sí")+COUNTIFS(Sesiones!$V$4:$V$78,A8,Sesiones!$AZ$4:$AZ$78,"Sí") -> 0
A9: S06 | B9: renovacion_licencia | C9: El permiso de funcionamiento de tu negocio ya se venció y quieres saber qué tienes que hacer para dejarlo vigente otra vez. | D9: =COUNTIFS(Sesiones!$T$4:$T$78,A9,Sesiones!$AZ$4:$AZ$78,"Sí")+COUNTIFS(Sesiones!$U$4:$U$78,A9,Sesiones!$AZ$4:$AZ$78,"Sí")+COUNTIFS(Sesiones!$V$4:$V$78,A9,Sesiones!$AZ$4:$AZ$78,"Sí") -> 0
A10: S07 | B10: consulta_deuda_predial | C10: Quieres saber si debes impuestos por tu casa o terreno, y cuánto sería. | D10: =COUNTIFS(Sesiones!$T$4:$T$78,A10,Sesiones!$AZ$4:$AZ$78,"Sí")+COUNTIFS(Sesiones!$U$4:$U$78,A10,Sesiones!$AZ$4:$AZ$78,"Sí")+COUNTIFS(Sesiones!$V$4:$V$78,A10,Sesiones!$AZ$4:$AZ$78,"Sí") -> 0
A11: S08 | B11: pago_predial_como | C11: Ya sabes que debes pagar el impuesto de tu casa y quieres saber dónde o de qué forma puedes hacerlo. | D11: =COUNTIFS(Sesiones!$T$4:$T$78,A11,Sesiones!$AZ$4:$AZ$78,"Sí")+COUNTIFS(Sesiones!$U$4:$U$78,A11,Sesiones!$AZ$4:$AZ$78,"Sí")+COUNTIFS(Sesiones!$V$4:$V$78,A11,Sesiones!$AZ$4:$AZ$78,"Sí") -> 0
A12: S09 | B12: pago_arbitrios | C12: Te llegó un cobro por el recojo de basura, la limpieza de calles y el serenazgo, y quieres saber cómo pagarlo. | D12: =COUNTIFS(Sesiones!$T$4:$T$78,A12,Sesiones!$AZ$4:$AZ$78,"Sí")+COUNTIFS(Sesiones!$U$4:$U$78,A12,Sesiones!$AZ$4:$AZ$78,"Sí")+COUNTIFS(Sesiones!$V$4:$V$78,A12,Sesiones!$AZ$4:$AZ$78,"Sí") -> 0
A13: S10 | B13: impuesto_alcabala | C13: Acabas de comprar un terreno y te dijeron que hay un impuesto por esa compra; quieres saber de qué trata y cómo se paga. | D13: =COUNTIFS(Sesiones!$T$4:$T$78,A13,Sesiones!$AZ$4:$AZ$78,"Sí")+COUNTIFS(Sesiones!$U$4:$U$78,A13,Sesiones!$AZ$4:$AZ$78,"Sí")+COUNTIFS(Sesiones!$V$4:$V$78,A13,Sesiones!$AZ$4:$AZ$78,"Sí") -> 0
A14: S11 | B14: fraccionamiento_deuda | C14: Debes varios años de impuestos municipales y no puedes pagar todo de golpe; quieres saber si puedes pagarlo poco a poco. | D14: =COUNTIFS(Sesiones!$T$4:$T$78,A14,Sesiones!$AZ$4:$AZ$78,"Sí")+COUNTIFS(Sesiones!$U$4:$U$78,A14,Sesiones!$AZ$4:$AZ$78,"Sí")+COUNTIFS(Sesiones!$V$4:$V$78,A14,Sesiones!$AZ$4:$AZ$78,"Sí") -> 0
A15: S12 | B15: constancia_no_adeudo | C15: Te piden un papel que demuestre que no tienes deudas con la municipalidad y quieres saber cómo conseguirlo. | D15: =COUNTIFS(Sesiones!$T$4:$T$78,A15,Sesiones!$AZ$4:$AZ$78,"Sí")+COUNTIFS(Sesiones!$U$4:$U$78,A15,Sesiones!$AZ$4:$AZ$78,"Sí")+COUNTIFS(Sesiones!$V$4:$V$78,A15,Sesiones!$AZ$4:$AZ$78,"Sí") -> 0
... A59: S56 | B59: repetir_informacion | C59: El asistente te dio una información pero no alcanzaste a leerla ni a anotarla. ¿Cómo le pedirías que te la repita? | D59: =COUNTIFS(Sesiones!$T$4:$T$78,A59,Sesiones!$AZ$4:$AZ$78,"Sí")+COUNTIFS(Sesiones!$U$4:$U$78,A59,Sesiones!$AZ$4:$AZ$78,"Sí")+COUNTIFS(Sesiones!$V$4:$V$78,A59,Sesiones!$AZ$4:$AZ$78,"Sí") -> 0

Sheet Parametros
A1: Parámetros y listas
A2: Celdas amarillas = valores editables. Las listas alimentan los menús desplegables de Sesiones.
A3: Rango de tiempo (línea base) | B3: Minutos (punto medio) | F3: Rango de edad | G3: Sí / No | H3: Categoría del trámite | I3: Veces que volvió | J3: ¿Correcta?
A4: Menos de 15 min | B4: 7.5 | F4: 18–29 | G4: Sí | H4: Licencias y autorizaciones | I4: Ninguna, se resolvió a la primera | J4: Sí
A5: 15–30 min | B5: 22.5 | F5: 30–44 | G5: No | H5: Tributos y pagos municipales | I5: 1 vez | J5: Parcial
A6: 30–60 min | B6: 45 | F6: 45–59 | H6: Trámites documentarios | I6: 2 a 3 veces | J6: No
A7: 1–2 horas | B7: 90 | F7: 60 a más | H7: Defensa civil y seguridad ciudadana | I7: Más de 3 veces
A8: 2–4 horas | B8: 180 | H8: Registro civil
A9: Más de 4 horas / varios días | B9: 300 | H9: Servicios públicos
A10: Supuesto: se usa el punto medio de cada rango; para «Más de 4 horas / varios días» se asume 300 min (5 h). Es un supuesto editable. | H10: Reclamos y quejas
H11: Información general / otro
A13: Parámetro | B13: Valor | C13: Fuente / criterio
A14: Meta de sesiones elegibles y completas | B14: 60 | C14: Decisión del tesista: piloto exploratorio de n = 60 (reduce los 120 del protocolo V1.2).
A15: Meta de reducción del tiempo | B15: 0.6 | C15: Hipótesis de la tesis: reducción ≥ 60 %.
A16: Meta de satisfacción (Likert 1–5) | B16: 4 | C16: Hipótesis de la tesis: Likert ≥ 4.0 sobre 5.
A17: Alfa de Cronbach mínimo | B17: 0.7 | C17: Criterio del pre-piloto formal del protocolo V1.2.
A18: Tope de tiempo por consulta (segundos) | B18: 180 | C18: Regla de la guía de aplicación: se corta a los 180 s sin respuesta útil. Solo informativo.
A19: Máximo de mensajes por consulta | B19: 3 | C19: Regla de la guía de aplicación. Solo informativo.
A20: Modelo congelado (nombre / versión) | C20: Anótalo antes de la primera sesión; no se cambia durante las sesiones.
A21: Fecha de congelamiento del modelo | C21: Anótala junto con la versión.

Sheet Calc
A1: Cálculo auxiliar del alfa de Cronbach
A2: Solo fórmulas. Copia los ítems 1–8 de las sesiones elegibles y completas; las demás filas quedan vacías para no distorsionar la varianza.
A3: Código | B3: Ítem 1 | C3: Ítem 2 | D3: Ítem 3 | E3: Ítem 4 | F3: Ítem 5 | G3: Ítem 6 | H3: Ítem 7 | I3: Ítem 8 | J3: Total
A4: =Sesiones!A4 -> SA01 | B4: =IF(Sesiones!AZ4="Sí",Sesiones!AO4,"") | C4: =IF(Sesiones!AZ4="Sí",Sesiones!AP4,"") | D4: =IF(Sesiones!AZ4="Sí",Sesiones!AQ4,"") | E4: =IF(Sesiones!AZ4="Sí",Sesiones!AR4,"") | F4: =IF(Sesiones!AZ4="Sí",Sesiones!AS4,"") | G4: =IF(Sesiones!AZ4="Sí",Sesiones!AT4,"") | H4: =IF(Sesiones!AZ4="Sí",Sesiones!AU4,"") | I4: =IF(Sesiones!AZ4="Sí",Sesiones!AV4,"") | J4: =IF(Sesiones!AZ4="Sí",Sesiones!BK4,"")
A5: =Sesiones!A5 -> SA02 | B5: =IF(Sesiones!AZ5="Sí",Sesiones!AO5,"") | C5: =IF(Sesiones!AZ5="Sí",Sesiones!AP5,"") | D5: =IF(Sesiones!AZ5="Sí",Sesiones!AQ5,"") | E5: =IF(Sesiones!AZ5="Sí",Sesiones!AR5,"") | F5: =IF(Sesiones!AZ5="Sí",Sesiones!AS5,"") | G5: =IF(Sesiones!AZ5="Sí",Sesiones!AT5,"") | H5: =IF(Sesiones!AZ5="Sí",Sesiones!AU5,"") | I5: =IF(Sesiones!AZ5="Sí",Sesiones!AV5,"") | J5: =IF(Sesiones!AZ5="Sí",Sesiones!BK5,"")
A6: =Sesiones!A6 -> SA03 | B6: =IF(Sesiones!AZ6="Sí",Sesiones!AO6,"") | C6: =IF(Sesiones!AZ6="Sí",Sesiones!AP6,"") | D6: =IF(Sesiones!AZ6="Sí",Sesiones!AQ6,"") | E6: =IF(Sesiones!AZ6="Sí",Sesiones!AR6,"") | F6: =IF(Sesiones!AZ6="Sí",Sesiones!AS6,"") | G6: =IF(Sesiones!AZ6="Sí",Sesiones!AT6,"") | H6: =IF(Sesiones!AZ6="Sí",Sesiones!AU6,"") | I6: =IF(Sesiones!AZ6="Sí",Sesiones!AV6,"") | J6: =IF(Sesiones!AZ6="Sí",Sesiones!BK6,"")
A7: =Sesiones!A7 -> SA04 | B7: =IF(Sesiones!AZ7="Sí",Sesiones!AO7,"") | C7: =IF(Sesiones!AZ7="Sí",Sesiones!AP7,"") | D7: =IF(Sesiones!AZ7="Sí",Sesiones!AQ7,"") | E7: =IF(Sesiones!AZ7="Sí",Sesiones!AR7,"") | F7: =IF(Sesiones!AZ7="Sí",Sesiones!AS7,"") | G7: =IF(Sesiones!AZ7="Sí",Sesiones!AT7,"") | H7: =IF(Sesiones!AZ7="Sí",Sesiones!AU7,"") | I7: =IF(Sesiones!AZ7="Sí",Sesiones!AV7,"") | J7: =IF(Sesiones!AZ7="Sí",Sesiones!BK7,"")
A8: =Sesiones!A8 -> SA05 | B8: =IF(Sesiones!AZ8="Sí",Sesiones!AO8,"") | C8: =IF(Sesiones!AZ8="Sí",Sesiones!AP8,"") | D8: =IF(Sesiones!AZ8="Sí",Sesiones!AQ8,"") | E8: =IF(Sesiones!AZ8="Sí",Sesiones!AR8,"") | F8: =IF(Sesiones!AZ8="Sí",Sesiones!AS8,"") | G8: =IF(Sesiones!AZ8="Sí",Sesiones!AT8,"") | H8: =IF(Sesiones!AZ8="Sí",Sesiones!AU8,"") | I8: =IF(Sesiones!AZ8="Sí",Sesiones!AV8,"") | J8: =IF(Sesiones!AZ8="Sí",Sesiones!BK8,"")
A9: =Sesiones!A9 -> SA06 | B9: =IF(Sesiones!AZ9="Sí",Sesiones!AO9,"") | C9: =IF(Sesiones!AZ9="Sí",Sesiones!AP9,"") | D9: =IF(Sesiones!AZ9="Sí",Sesiones!AQ9,"") | E9: =IF(Sesiones!AZ9="Sí",Sesiones!AR9,"") | F9: =IF(Sesiones!AZ9="Sí",Sesiones!AS9,"") | G9: =IF(Sesiones!AZ9="Sí",Sesiones!AT9,"") | H9: =IF(Sesiones!AZ9="Sí",Sesiones!AU9,"") | I9: =IF(Sesiones!AZ9="Sí",Sesiones!AV9,"") | J9: =IF(Sesiones!AZ9="Sí",Sesiones!BK9,"")
A10: =Sesiones!A10 -> SA07 | B10: =IF(Sesiones!AZ10="Sí",Sesiones!AO10,"") | C10: =IF(Sesiones!AZ10="Sí",Sesiones!AP10,"") | D10: =IF(Sesiones!AZ10="Sí",Sesiones!AQ10,"") | E10: =IF(Sesiones!AZ10="Sí",Sesiones!AR10,"") | F10: =IF(Sesiones!AZ10="Sí",Sesiones!AS10,"") | G10: =IF(Sesiones!AZ10="Sí",Sesiones!AT10,"") | H10: =IF(Sesiones!AZ10="Sí",Sesiones!AU10,"") | I10: =IF(Sesiones!AZ10="Sí",Sesiones!AV10,"") | J10: =IF(Sesiones!AZ10="Sí",Sesiones!BK10,"")
A11: =Sesiones!A11 -> SA08 | B11: =IF(Sesiones!AZ11="Sí",Sesiones!AO11,"") | C11: =IF(Sesiones!AZ11="Sí",Sesiones!AP11,"") | D11: =IF(Sesiones!AZ11="Sí",Sesiones!AQ11,"") | E11: =IF(Sesiones!AZ11="Sí",Sesiones!AR11,"") | F11: =IF(Sesiones!AZ11="Sí",Sesiones!AS11,"") | G11: =IF(Sesiones!AZ11="Sí",Sesiones!AT11,"") | H11: =IF(Sesiones!AZ11="Sí",Sesiones!AU11,"") | I11: =IF(Sesiones!AZ11="Sí",Sesiones!AV11,"") | J11: =IF(Sesiones!AZ11="Sí",Sesiones!BK11,"")
A12: =Sesiones!A12 -> SA09 | B12: =IF(Sesiones!AZ12="Sí",Sesiones!AO12,"") | C12: =IF(Sesiones!AZ12="Sí",Sesiones!AP12,"") | D12: =IF(Sesiones!AZ12="Sí",Sesiones!AQ12,"") | E12: =IF(Sesiones!AZ12="Sí",Sesiones!AR12,"") | F12: =IF(Sesiones!AZ12="Sí",Sesiones!AS12,"") | G12: =IF(Sesiones!AZ12="Sí",Sesiones!AT12,"") | H12: =IF(Sesiones!AZ12="Sí",Sesiones!AU12,"") | I12: =IF(Sesiones!AZ12="Sí",Sesiones!AV12,"") | J12: =IF(Sesiones!AZ12="Sí",Sesiones!BK12,"")
A13: =Sesiones!A13 -> SA10 | B13: =IF(Sesiones!AZ13="Sí",Sesiones!AO13,"") | C13: =IF(Sesiones!AZ13="Sí",Sesiones!AP13,"") | D13: =IF(Sesiones!AZ13="Sí",Sesiones!AQ13,"") | E13: =IF(Sesiones!AZ13="Sí",Sesiones!AR13,"") | F13: =IF(Sesiones!AZ13="Sí",Sesiones!AS13,"") | G13: =IF(Sesiones!AZ13="Sí",Sesiones!AT13,"") | H13: =IF(Sesiones!AZ13="Sí",Sesiones!AU13,"") | I13: =IF(Sesiones!AZ13="Sí",Sesiones!AV13,"") | J13: =IF(Sesiones!AZ13="Sí",Sesiones!BK13,"")
A14: =Sesiones!A14 -> SA11 | B14: =IF(Sesiones!AZ14="Sí",Sesiones!AO14,"") | C14: =IF(Sesiones!AZ14="Sí",Sesiones!AP14,"") | D14: =IF(Sesiones!AZ14="Sí",Sesiones!AQ14,"") | E14: =IF(Sesiones!AZ14="Sí",Sesiones!AR14,"") | F14: =IF(Sesiones!AZ14="Sí",Sesiones!AS14,"") | G14: =IF(Sesiones!AZ14="Sí",Sesiones!AT14,"") | H14: =IF(Sesiones!AZ14="Sí",Sesiones!AU14,"") | I14: =IF(Sesiones!AZ14="Sí",Sesiones!AV14,"") | J14: =IF(Sesiones!AZ14="Sí",Sesiones!BK14,"")
A15: =Sesiones!A15 -> SA12 | B15: =IF(Sesiones!AZ15="Sí",Sesiones!AO15,"") | C15: =IF(Sesiones!AZ15="Sí",Sesiones!AP15,"") | D15: =IF(Sesiones!AZ15="Sí",Sesiones!AQ15,"") | E15: =IF(Sesiones!AZ15="Sí",Sesiones!AR15,"") | F15: =IF(Sesiones!AZ15="Sí",Sesiones!AS15,"") | G15: =IF(Sesiones!AZ15="Sí",Sesiones!AT15,"") | H15: =IF(Sesiones!AZ15="Sí",Sesiones!AU15,"") | I15: =IF(Sesiones!AZ15="Sí",Sesiones!AV15,"") | J15: =IF(Sesiones!AZ15="Sí",Sesiones!BK15,"")
... A78: =Sesiones!A78 -> SA75 | B78: =IF(Sesiones!AZ78="Sí",Sesiones!AO78,"") | C78: =IF(Sesiones!AZ78="Sí",Sesiones!AP78,"") | D78: =IF(Sesiones!AZ78="Sí",Sesiones!AQ78,"") | E78: =IF(Sesiones!AZ78="Sí",Sesiones!AR78,"") | F78: =IF(Sesiones!AZ78="Sí",Sesiones!AS78,"") | G78: =IF(Sesiones!AZ78="Sí",Sesiones!AT78,"") | H78: =IF(Sesiones!AZ78="Sí",Sesiones!AU78,"") | I78: =IF(Sesiones!AZ78="Sí",Sesiones!AV78,"") | J78: =IF(Sesiones!AZ78="Sí",Sesiones!BK78,"")

Sheet Notas
A1: Notas de uso, criterios y fuentes
A3: Cómo usar
A4: 1. Cada persona de la sesión asistida recibe un código SA01, SA02… (sin relación con su nombre). Las tres tarjetas de situación salen solas en las columnas Tarjeta 1–3 de Sesiones.
A5: 2. Después de cada sesión, transcribe el formulario en la fila de la persona (celdas amarillas). No corrijas respuestas. Los tiempos van en segundos.
A6: 3. «Elegible y completa» marca con Sí las sesiones que entran al análisis: trámite presencial en los últimos 12 meses, línea base, 3 tiempos y los 9 ítems post respondidos.
A7: 4. Resumen calcula solo con las elegibles y completas. Las no elegibles se registran para llevar la cuenta y se reemplazan por otra persona.
A9: Criterios
A10: • Piloto exploratorio de n = 60 sesiones elegibles (decisión del tesista; reduce los 120 del protocolo V1.2). Sirve para mostrar viabilidad, no para confirmar hipótesis.
A11: • Diseño de una sola sesión: la línea base es recordada (Parte 1 del formulario) y el tiempo con el asistente se mide en la misma visita (Parte 2). Se declara como limitación (sesgo de recuerdo y de novedad).
A12: • Modelo congelado antes de la primera sesión (Parametros). Las consultas escritas quedan registradas como conjunto de prueba final: no se usan para ajustar el modelo durante las sesiones.
A13: • El ítem 9 de satisfacción empareja con P10 (misma redacción, referida al asistente). La pregunta complementaria de tiempo estimado para la consulta 1 no reemplaza la línea base de la Parte 1.
A14: • Tiempo sin respuesta útil: se registra el tiempo de corte (180 s o 3 mensajes) y la consulta se marca «No» en «obtuvo lo que necesitaba».
... A21: • Colores: azul = valor escrito a mano o dato fijo; negro = fórmula; verde = vínculo a otra hoja.
